Workbook

Sheet Read Me
A1: ROOTWAKE — Species & Systems Database v0.1
A3: What this is | B3: The master data file for Rootwake's flora. Every recipe, order, and market price reads from these tables. The game repo (SacredGrove) keeps this workbook in data/ and reads the Species and Plants tabs with `npm run data`, which validates them and writes src/data/plants.gen.json.
A4: Design pyramid | B4: Base ≈ filler/food/carriers; Workhorse = reliable single actions; Rare Active = signature effects. Target ratio ~60/30/10 by count; see Stats tab (live formulas).
A5: Setting | B5: Southern Illinois-style ecology (Shawnee Hills, bottomlands, tallgrass remnants, limestone bluffs) plus one fictional biome — the Mycelial Hollow — where the Network surfaces. Real species carry folk-traditional uses as GAME effects only; no real dosing is modeled.
A6: Hidden values | B6: Compound codes + strength (1–10) are hidden from the player. Taste, smell, drying, burning and extraction each reveal one layer in the Field Journal.
A7: Toxicity | B7: 0–10. ≥5 = harmful in game; ≥9 = lethal species, sellable only to licensed buyers, and handling without gloves applies a status. Taste column shows DO NOT TASTE for lethal species — tasting them is an in-game death/injury event.
A8: Months | B8: 1–12. If Harvest Start > Harvest End the window wraps the new year (e.g. 10→3 = Oct–Mar). Seed Month 0 = propagated by division/spores only.
A9: Editing | B9: Blue text = hand-entered inputs; edit freely. Black = formulas (Seasonal Calendar, Stats, Recipe value). Add species by appending rows to the Species tab; the calendar and stats extend if you copy the formula rows down.
A10: Fictional species | B10: Marked '(fictional)' in the Latin name. All other species are real and native or naturalized to the Midwest.
A11: Plants tab | B11: Ecology for the game world: one row per living plant (Species rows are harvestable PRODUCTS and join on Latin Name, so Common Mullein + Mullein Flower share one plant). Light/moisture/disturbance/fertility are 0-1 optimum + tolerance (a Gaussian width). DOY = day of year (Mar 1 = 60, Jul 1 = 182, Oct 1 = 274); a green-up later than dieback means the plant is active across winter (winter annuals). C-value approximates Illinois Floristic Quality conservatism: 6+ only grows on never-plowed ground. Mow Tolerance 0-3 = the heaviest mowing it survives (3 = weekly lawn). The game reads this tab: run `npm run data` in SacredGrove after editing.

Sheet Species
A1: ID | B1: Common Name | C1: Latin Name | D1: Tier | E1: Biome | F1: Part Used | G1: Harvest Start | H1: Harvest End | I1: Seed Month | J1: Compound 1 | K1: Str 1 | L1: Compound 2 | M1: Str 2 | N1: Compound 3 | O1: Str 3 | P1: Toxicity (0-10) | Q1: Taste (journal) | R1: Smell (journal) | S1: Primary Use / Effect | T1: Rarity (1-5) | U1: Base Price (c) | V1: Shelf Life (days) | W1: On Plants tab?
A2: SP001 | B2: Lamb's Quarters | C2: Chenopodium album | D2: Base | E2: Disturbed Ground | F2: Leaf | G2: 5 | H2: 8 | I2: 9 | J2: SUG | K2: 3 | L2: ACI | M2: 2 | P2: 1 | Q2: Spinach-like | R2: Earthy | S2: Filler / food | T2: 1 | U2: =ROUND(2*T2^2*IF(D2="Rare Active",6,IF(D2="Workhorse",2,1))+(K2+M2+O2)/2,0) -> 5 | V2: 45 | W2: =IF(COUNTIF(Plants!$A$2:$A$1000,C2)>0,"yes","") -> yes
A3: SP002 | B3: Chickweed | C3: Stellaria media | D3: Base | E3: Disturbed Ground | F3: Whole | G3: 3 | H3: 5 | I3: 5 | J3: MUC | K3: 3 | L3: SAP | M3: 1 | P3: 0 | Q3: Fresh, corn-silk | R3: Faint | S3: Cooling base | T3: 1 | U3: =ROUND(2*T3^2*IF(D3="Rare Active",6,IF(D3="Workhorse",2,1))+(K3+M3+O3)/2,0) -> 4 | V3: 40 | W3: =IF(COUNTIF(Plants!$A$2:$A$1000,C3)>0,"yes","") -> yes
A4: SP003 | B4: Purple Deadnettle | C4: Lamium purpureum | D4: Base | E4: Disturbed Ground | F4: Whole | G4: 3 | H4: 5 | I4: 5 | J4: FLA | K4: 2 | L4: VOL | M4: 1 | P4: 0 | Q4: Grassy | R4: Musty mint | S4: Filler | T4: 1 | U4: =ROUND(2*T4^2*IF(D4="Rare Active",6,IF(D4="Workhorse",2,1))+(K4+M4+O4)/2,0) -> 4 | V4: 40 | W4: =IF(COUNTIF(Plants!$A$2:$A$1000,C4)>0,"yes","") -> yes
A5: SP004 | B5: Henbit | C5: Lamium amplexicaule | D5: Base | E5: Disturbed Ground | F5: Whole | G5: 3 | H5: 5 | I5: 5 | J5: FLA | K5: 2 | P5: 0 | Q5: Mild | R5: Faint | S5: Filler | T5: 1 | U5: =ROUND(2*T5^2*IF(D5="Rare Active",6,IF(D5="Workhorse",2,1))+(K5+M5+O5)/2,0) -> 3 | V5: 40 | W5: =IF(COUNTIF(Plants!$A$2:$A$1000,C5)>0,"yes","") -> yes
A6: SP005 | B6: Dandelion | C6: Taraxacum officinale | D6: Workhorse | E6: Disturbed Ground | F6: Root | G6: 3 | H6: 11 | I6: 5 | J6: BIT | K6: 5 | L6: SUG | M6: 3 | N6: LAT | O6: 2 | P6: 0 | Q6: Bitter | R6: Earthy | S6: Digestive bitter / liver tonic | T6: 1 | U6: =ROUND(2*T6^2*IF(D6="Rare Active",6,IF(D6="Workhorse",2,1))+(K6+M6+O6)/2,0) -> 9 | V6: 120 | W6: =IF(COUNTIF(Plants!$A$2:$A$1000,C6)>0,"yes","") -> yes
A7: SP006 | B7: Common Blue Violet | C7: Viola sororia | D7: Base | E7: Upland Forest | F7: Leaf | G7: 3 | H7: 6 | I7: 6 | J7: MUC | K7: 4 | L7: SAP | M7: 1 | P7: 0 | Q7: Mild, slick | R7: Faint sweet | S7: Thickener | T7: 2 | U7: =ROUND(2*T7^2*IF(D7="Rare Active",6,IF(D7="Workhorse",2,1))+(K7+M7+O7)/2,0) -> 11 | V7: 45 | W7: =IF(COUNTIF(Plants!$A$2:$A$1000,C7)>0,"yes","") -> yes
A8: SP007 | B8: Cleavers | C8: Galium aparine | D8: Base | E8: Bottomland Forest | F8: Whole | G8: 4 | H8: 6 | I8: 6 | J8: COU | K8: 1 | L8: ACI | M8: 2 | P8: 0 | Q8: Green | R8: Hay | S8: Strainer / lymph wash | T8: 1 | U8: =ROUND(2*T8^2*IF(D8="Rare Active",6,IF(D8="Workhorse",2,1))+(K8+M8+O8)/2,0) -> 4 | V8: 40 | W8: =IF(COUNTIF(Plants!$A$2:$A$1000,C8)>0,"yes","") -> yes
A9: SP008 | B9: Wood Sorrel | C9: Oxalis stricta | D9: Base | E9: Disturbed Ground | F9: Leaf | G9: 5 | H9: 10 | I9: 7 | J9: ACI | K9: 5 | P9: 1 | Q9: Sour, lemony | R9: None | S9: Acidifier | T9: 1 | U9: =ROUND(2*T9^2*IF(D9="Rare Active",6,IF(D9="Workhorse",2,1))+(K9+M9+O9)/2,0) -> 5 | V9: 45 | W9: =IF(COUNTIF(Plants!$A$2:$A$1000,C9)>0,"yes","") -> yes
A10: SP009 | B10: Sheep Sorrel | C10: Rumex acetosella | D10: Base | E10: Prairie | F10: Leaf | G10: 4 | H10: 7 | I10: 7 | J10: ACI | K10: 4 | L10: TAN | M10: 2 | P10: 1 | Q10: Sour | R10: None | S10: Acidifier | T10: 1 | U10: =ROUND(2*T10^2*IF(D10="Rare Active",6,IF(D10="Workhorse",2,1))+(K10+M10+O10)/2,0) -> 5 | V10: 45 | W10: =IF(COUNTIF(Plants!$A$2:$A$1000,C10)>0,"yes","") -> yes
A11: SP010 | B11: Curly Dock | C11: Rumex crispus | D11: Workhorse | E11: Disturbed Ground | F11: Root | G11: 9 | H11: 11 | I11: 8 | J11: TAN | K11: 4 | L11: GLY | M11: 3 | N11: PIG | O11: 2 | P11: 1 | Q11: Bitter, astringent | R11: Earthy | S11: Purgative / yellow dye | T11: 1 | U11: =ROUND(2*T11^2*IF(D11="Rare Active",6,IF(D11="Workhorse",2,1))+(K11+M11+O11)/2,0) -> 9 | V11: 120 | W11: =IF(COUNTIF(Plants!$A$2:$A$1000,C11)>0,"yes","") -> yes
A12: SP011 | B12: Red Clover | C12: Trifolium pratense | D12: Base | E12: Prairie | F12: Flower | G12: 5 | H12: 8 | I12: 8 | J12: FLA | K12: 3 | L12: COU | M12: 2 | N12: SUG | O12: 2 | P12: 0 | Q12: Sweet | R12: Honeyed | S12: Flavor mask (sweet) | T12: 1 | U12: =ROUND(2*T12^2*IF(D12="Rare Active",6,IF(D12="Workhorse",2,1))+(K12+M12+O12)/2,0) -> 6 | V12: 30 | W12: =IF(COUNTIF(Plants!$A$2:$A$1000,C12)>0,"yes","") -> yes
A13: SP012 | B13: White Clover | C13: Trifolium repens | D13: Base | E13: Disturbed Ground | F13: Flower | G13: 5 | H13: 9 | I13: 8 | J13: SUG | K13: 2 | L13: FLA | M13: 1 | P13: 0 | Q13: Sweet | R13: Faint | S13: Bee forage / filler | T13: 1 | U13: =ROUND(2*T13^2*IF(D13="Rare Active",6,IF(D13="Workhorse",2,1))+(K13+M13+O13)/2,0) -> 4 | V13: 30 | W13: =IF(COUNTIF(Plants!$A$2:$A$1000,C13)>0,"yes","") -> yes
A14: SP013 | B14: Wild Strawberry | C14: Fragaria virginiana | D14: Base | E14: Prairie | F14: Fruit | G14: 5 | H14: 6 | I14: 6 | J14: SUG | K14: 4 | L14: ACI | M14: 2 | N14: ANT | O14: 2 | P14: 0 | Q14: Sweet-tart | R14: Fruity | S14: Flavor mask (fruit) | T14: 2 | U14: =ROUND(2*T14^2*IF(D14="Rare Active",6,IF(D14="Workhorse",2,1))+(K14+M14+O14)/2,0) -> 12 | V14: 10 | W14: =IF(COUNTIF(Plants!$A$2:$A$1000,C14)>0,"yes","") -> yes
A15: SP014 | B15: Riverbank Grape | C15: Vitis riparia | D15: Base | E15: Riverbank | F15: Fruit | G15: 8 | H15: 10 | I15: 9 | J15: SUG | K15: 4 | L15: ACI | M15: 3 | N15: ANT | O15: 3 | P15: 0 | Q15: Tart | R15: Musky | S15: Ferment base | T15: 2 | U15: =ROUND(2*T15^2*IF(D15="Rare Active",6,IF(D15="Workhorse",2,1))+(K15+M15+O15)/2,0) -> 13 | V15: 10 | W15: =IF(COUNTIF(Plants!$A$2:$A$1000,C15)>0,"yes","") -> yes
A16: SP015 | B16: Black Raspberry | C16: Rubus occidentalis | D16: Base | E16: Oak Savanna | F16: Fruit | G16: 6 | H16: 7 | I16: 7 | J16: SUG | K16: 4 | L16: ANT | M16: 4 | P16: 0 | Q16: Sweet | R16: Berry | S16: Dye: purple / flavor | T16: 2 | U16: =ROUND(2*T16^2*IF(D16="Rare Active",6,IF(D16="Workhorse",2,1))+(K16+M16+O16)/2,0) -> 12 | V16: 10 | W16: =IF(COUNTIF(Plants!$A$2:$A$1000,C16)>0,"yes","") -> yes
A17: SP016 | B17: Blackberry Leaf | C17: Rubus allegheniensis | D17: Base | E17: Oak Savanna | F17: Leaf | G17: 5 | H17: 9 | I17: 8 | J17: TAN | K17: 5 | P17: 0 | Q17: Astringent | R17: Tea-like | S17: Astringent base | T17: 2 | U17: =ROUND(2*T17^2*IF(D17="Rare Active",6,IF(D17="Workhorse",2,1))+(K17+M17+O17)/2,0) -> 11 | V17: 45 | W17: =IF(COUNTIF(Plants!$A$2:$A$1000,C17)>0,"yes","") -> yes
A18: SP017 | B18: Red Mulberry | C18: Morus rubra | D18: Base | E18: Bottomland Forest | F18: Fruit | G18: 6 | H18: 7 | I18: 7 | J18: SUG | K18: 5 | L18: ANT | M18: 3 | P18: 0 | Q18: Very sweet | R18: Fruity | S18: Sweetener / dye | T18: 2 | U18: =ROUND(2*T18^2*IF(D18="Rare Active",6,IF(D18="Workhorse",2,1))+(K18+M18+O18)/2,0) -> 12 | V18: 10 | W18: =IF(COUNTIF(Plants!$A$2:$A$1000,C18)>0,"yes","") -> yes
A19: SP018 | B19: Pawpaw | C19: Asimina triloba | D19: Base | E19: Bottomland Forest | F19: Fruit | G19: 9 | H19: 10 | I19: 10 | J19: SUG | K19: 5 | P19: 1 | Q19: Custard, tropical | R19: Banana | S19: Sweetener (spoils fast) | T19: 3 | U19: =ROUND(2*T19^2*IF(D19="Rare Active",6,IF(D19="Workhorse",2,1))+(K19+M19+O19)/2,0) -> 21 | V19: 10 | W19: =IF(COUNTIF(Plants!$A$2:$A$1000,C19)>0,"yes","")
A20: SP019 | B20: Persimmon | C20: Diospyros virginiana | D20: Base | E20: Oak Savanna | F20: Fruit | G20: 10 | H20: 12 | I20: 11 | J20: SUG | K20: 6 | L20: TAN | M20: 3 | P20: 0 | Q20: Honey-sweet when ripe, chalky if not | R20: Date | S20: Sweetener | T20: 2 | U20: =ROUND(2*T20^2*IF(D20="Rare Active",6,IF(D20="Workhorse",2,1))+(K20+M20+O20)/2,0) -> 13 | V20: 10 | W20: =IF(COUNTIF(Plants!$A$2:$A$1000,C20)>0,"yes","") -> yes
A21: SP020 | B21: Shagbark Hickory Nut | C21: Carya ovata | D21: Base | E21: Upland Forest | F21: Seed | G21: 9 | H21: 10 | I21: 10 | J21: SUG | K21: 3 | L21: RES | M21: 1 | P21: 0 | Q21: Buttery | R21: Nutty | S21: Oil press | T21: 3 | U21: =ROUND(2*T21^2*IF(D21="Rare Active",6,IF(D21="Workhorse",2,1))+(K21+M21+O21)/2,0) -> 20 | V21: 300 | W21: =IF(COUNTIF(Plants!$A$2:$A$1000,C21)>0,"yes","") -> yes
A22: SP021 | B22: Black Walnut Hull | C22: Juglans nigra | D22: Workhorse | E22: Upland Forest | F22: Fruit | G22: 9 | H22: 10 | I22: 10 | J22: TAN | K22: 6 | L22: PIG | M22: 6 | P22: 2 | Q22: Harsh, bitter | R22: Citrus-resin | S22: Dye: brown / antifungal | T22: 3 | U22: =ROUND(2*T22^2*IF(D22="Rare Active",6,IF(D22="Workhorse",2,1))+(K22+M22+O22)/2,0) -> 42 | V22: 10 | W22: =IF(COUNTIF(Plants!$A$2:$A$1000,C22)>0,"yes","") -> yes
A23: SP022 | B23: White Oak Acorn | C23: Quercus alba | D23: Base | E23: Oak Savanna | F23: Seed | G23: 9 | H23: 11 | I23: 10 | J23: TAN | K23: 5 | L23: SUG | M23: 4 | P23: 1 | Q23: Astringent | R23: Nutty | S23: Starch (leach first) | T23: 2 | U23: =ROUND(2*T23^2*IF(D23="Rare Active",6,IF(D23="Workhorse",2,1))+(K23+M23+O23)/2,0) -> 13 | V23: 300 | W23: =IF(COUNTIF(Plants!$A$2:$A$1000,C23)>0,"yes","") -> yes
A24: SP023 | B24: White Oak Bark | C24: Quercus alba | D24: Workhorse | E24: Oak Savanna | F24: Bark | G24: 3 | H24: 5 | I24: 0 | J24: TAN | K24: 8 | P24: 0 | Q24: Extremely astringent | R24: Woody | S24: Wound wash / leather tanning | T24: 3 | U24: =ROUND(2*T24^2*IF(D24="Rare Active",6,IF(D24="Workhorse",2,1))+(K24+M24+O24)/2,0) -> 40 | V24: 240 | W24: =IF(COUNTIF(Plants!$A$2:$A$1000,C24)>0,"yes","") -> yes
A25: SP024 | B25: Shagbark Hickory Bark | C25: Carya ovata | D25: Base | E25: Upland Forest | F25: Bark | G25: 1 | H25: 12 | I25: 0 | J25: TAN | K25: 3 | L25: VOL | M25: 2 | N25: SUG | O25: 2 | P25: 0 | Q25: Smoky-sweet | R25: Maple-smoke | S25: Syrup base | T25: 3 | U25: =ROUND(2*T25^2*IF(D25="Rare Active",6,IF(D25="Workhorse",2,1))+(K25+M25+O25)/2,0) -> 22 | V25: 240 | W25: =IF(COUNTIF(Plants!$A$2:$A$1000,C25)>0,"yes","") -> yes
A26: SP025 | B26: Sugar Maple Sap | C26: Acer saccharum | D26: Base | E26: Upland Forest | F26: Sap | G26: 2 | H26: 3 | I26: 0 | J26: SUG | K26: 6 | P26: 0 | Q26: Faintly sweet | R26: None | S26: Syrup / solvent | T26: 3 | U26: =ROUND(2*T26^2*IF(D26="Rare Active",6,IF(D26="Workhorse",2,1))+(K26+M26+O26)/2,0) -> 21 | V26: 7 | W26: =IF(COUNTIF(Plants!$A$2:$A$1000,C26)>0,"yes","") -> yes
A27: SP026 | B27: Box Elder Sap | C27: Acer negundo | D27: Base | E27: Riverbank | F27: Sap | G27: 2 | H27: 3 | I27: 0 | J27: SUG | K27: 4 | P27: 0 | Q27: Faint | R27: None | S27: Syrup (weak) | T27: 2 | U27: =ROUND(2*T27^2*IF(D27="Rare Active",6,IF(D27="Workhorse",2,1))+(K27+M27+O27)/2,0) -> 10 | V27: 7 | W27: =IF(COUNTIF(Plants!$A$2:$A$1000,C27)>0,"yes","")
A28: SP027 | B28: Cattail Rhizome | C28: Typha latifolia | D28: Base | E28: Wetland | F28: Rhizome | G28: 10 | H28: 3 | I28: 8 | J28: SUG | K28: 5 | P28: 0 | Q28: Starchy | R28: Mud | S28: Starch / binder | T28: 2 | U28: =ROUND(2*T28^2*IF(D28="Rare Active",6,IF(D28="Workhorse",2,1))+(K28+M28+O28)/2,0) -> 11 | V28: 120 | W28: =IF(COUNTIF(Plants!$A$2:$A$1000,C28)>0,"yes","")
A29: SP028 | B29: Cattail Pollen | C29: Typha latifolia | D29: Base | E29: Wetland | F29: Flower | G29: 6 | H29: 6 | I29: 0 | J29: SUG | K29: 3 | L29: FLA | M29: 1 | P29: 0 | Q29: Corn-like | R29: Faint | S29: Flour / dusting powder | T29: 2 | U29: =ROUND(2*T29^2*IF(D29="Rare Active",6,IF(D29="Workhorse",2,1))+(K29+M29+O29)/2,0) -> 10 | V29: 30 | W29: =IF(COUNTIF(Plants!$A$2:$A$1000,C29)>0,"yes","")
A30: SP029 | B30: Broadleaf Arrowhead | C30: Sagittaria latifolia | D30: Base | E30: Wetland | F30: Rhizome | G30: 9 | H30: 11 | I30: 9 | J30: SUG | K30: 5 | P30: 0 | Q30: Potato | R30: Mud | S30: Starch | T30: 3 | U30: =ROUND(2*T30^2*IF(D30="Rare Active",6,IF(D30="Workhorse",2,1))+(K30+M30+O30)/2,0) -> 21 | V30: 120 | W30: =IF(COUNTIF(Plants!$A$2:$A$1000,C30)>0,"yes","")
A31: SP030 | B31: Wild Rice | C31: Zizania aquatica | D31: Base | E31: Wetland | F31: Seed | G31: 8 | H31: 9 | I31: 9 | J31: SUG | K31: 4 | P31: 0 | Q31: Nutty | R31: Grain | S31: Food filler | T31: 4 | U31: =ROUND(2*T31^2*IF(D31="Rare Active",6,IF(D31="Workhorse",2,1))+(K31+M31+O31)/2,0) -> 34 | V31: 300 | W31: =IF(COUNTIF(Plants!$A$2:$A$1000,C31)>0,"yes","")
A32: SP031 | B32: Pickerelweed | C32: Pontederia cordata | D32: Base | E32: Wetland | F32: Seed | G32: 8 | H32: 10 | I32: 9 | J32: SUG | K32: 3 | P32: 0 | Q32: Nutty | R32: Faint | S32: Filler | T32: 3 | U32: =ROUND(2*T32^2*IF(D32="Rare Active",6,IF(D32="Workhorse",2,1))+(K32+M32+O32)/2,0) -> 20 | V32: 300 | W32: =IF(COUNTIF(Plants!$A$2:$A$1000,C32)>0,"yes","")
A33: SP032 | B33: Sweetflag | C33: Acorus calamus | D33: Workhorse | E33: Wetland | F33: Rhizome | G33: 4 | H33: 10 | I33: 0 | J33: VOL | K33: 6 | L33: BIT | M33: 4 | P33: 3 | Q33: Bitter, ginger-like | R33: Spicy perfume | S33: Stimulant / voice clarity | T33: 3 | U33: =ROUND(2*T33^2*IF(D33="Rare Active",6,IF(D33="Workhorse",2,1))+(K33+M33+O33)/2,0) -> 41 | V33: 120 | W33: =IF(COUNTIF(Plants!$A$2:$A$1000,C33)>0,"yes","")
A34: SP033 | B34: Duckweed | C34: Lemna minor | D34: Base | E34: Wetland | F34: Whole | G34: 5 | H34: 9 | I34: 0 | J34: SUG | K34: 1 | L34: MUC | M34: 1 | P34: 0 | Q34: Bland | R34: Pond | S34: Compost accelerant | T34: 1 | U34: =ROUND(2*T34^2*IF(D34="Rare Active",6,IF(D34="Workhorse",2,1))+(K34+M34+O34)/2,0) -> 3 | V34: 40 | W34: =IF(COUNTIF(Plants!$A$2:$A$1000,C34)>0,"yes","")
A35: SP034 | B35: Common Reed | C35: Phragmites australis | D35: Base | E35: Wetland | F35: Root | G35: 3 | H35: 10 | I35: 10 | J35: SUG | K35: 3 | P35: 0 | Q35: Sweet-starchy | R35: Grassy | S35: Filler / straw | T35: 1 | U35: =ROUND(2*T35^2*IF(D35="Rare Active",6,IF(D35="Workhorse",2,1))+(K35+M35+O35)/2,0) -> 4 | V35: 120 | W35: =IF(COUNTIF(Plants!$A$2:$A$1000,C35)>0,"yes","")
A36: SP035 | B36: Field Horsetail | C36: Equisetum arvense | D36: Base | E36: Riverbank | F36: Whole | G36: 4 | H36: 7 | I36: 0 | J36: ACI | K36: 1 | L36: SAP | M36: 1 | P36: 2 | Q36: Gritty | R36: Grassy | S36: Abrasive / polish | T36: 2 | U36: =ROUND(2*T36^2*IF(D36="Rare Active",6,IF(D36="Workhorse",2,1))+(K36+M36+O36)/2,0) -> 9 | V36: 40 | W36: =IF(COUNTIF(Plants!$A$2:$A$1000,C36)>0,"yes","") -> yes
A37: SP036 | B37: Scouring Rush | C37: Equisetum hyemale | D37: Base | E37: Riverbank | F37: Whole | G37: 1 | H37: 12 | I37: 0 | J37: ACI | K37: 1 | P37: 2 | Q37: Gritty | R37: None | S37: Abrasive / tool sharpening | T37: 2 | U37: =ROUND(2*T37^2*IF(D37="Rare Active",6,IF(D37="Workhorse",2,1))+(K37+M37+O37)/2,0) -> 9 | V37: 40 | W37: =IF(COUNTIF(Plants!$A$2:$A$1000,C37)>0,"yes","")
A38: SP037 | B38: Jewelweed | C38: Impatiens capensis | D38: Workhorse | E38: Bottomland Forest | F38: Whole | G38: 6 | H38: 9 | I38: 9 | J38: SAP | K38: 3 | L38: MUC | M38: 3 | P38: 0 | Q38: Watery | R38: Green | S38: Itch & rash wash (counters Poison Ivy) | T38: 2 | U38: =ROUND(2*T38^2*IF(D38="Rare Active",6,IF(D38="Workhorse",2,1))+(K38+M38+O38)/2,0) -> 19 | V38: 40 | W38: =IF(COUNTIF(Plants!$A$2:$A$1000,C38)>0,"yes","") -> yes
A39: SP038 | B39: Stinging Nettle | C39: Urtica dioica | D39: Workhorse | E39: Bottomland Forest | F39: Leaf | G39: 4 | H39: 6 | I39: 8 | J39: FLA | K39: 3 | L39: ACI | M39: 3 | N39: SUG | O39: 2 | P39: 0 | Q39: Rich, green | R39: Spinach | S39: Strength tonic | T39: 2 | U39: =ROUND(2*T39^2*IF(D39="Rare Active",6,IF(D39="Workhorse",2,1))+(K39+M39+O39)/2,0) -> 20 | V39: 45 | W39: =IF(COUNTIF(Plants!$A$2:$A$1000,C39)>0,"yes","") -> yes
A40: SP039 | B40: Wood Nettle | C40: Laportea canadensis | D40: Base | E40: Bottomland Forest | F40: Leaf | G40: 4 | H40: 6 | I40: 8 | J40: ACI | K40: 2 | L40: FLA | M40: 1 | P40: 0 | Q40: Green | R40: Faint | S40: Fiber / filler | T40: 2 | U40: =ROUND(2*T40^2*IF(D40="Rare Active",6,IF(D40="Workhorse",2,1))+(K40+M40+O40)/2,0) -> 10 | V40: 45 | W40: =IF(COUNTIF(Plants!$A$2:$A$1000,C40)>0,"yes","")
A41: SP040 | B41: Burdock | C41: Arctium minus | D41: Workhorse | E41: Disturbed Ground | F41: Root | G41: 9 | H41: 11 | I41: 9 | J41: SUG | K41: 4 | L41: BIT | M41: 3 | P41: 0 | Q41: Earthy-sweet | R41: Soil | S41: Blood cleanse / skin | T41: 2 | U41: =ROUND(2*T41^2*IF(D41="Rare Active",6,IF(D41="Workhorse",2,1))+(K41+M41+O41)/2,0) -> 20 | V41: 120 | W41: =IF(COUNTIF(Plants!$A$2:$A$1000,C41)>0,"yes","") -> yes
A42: SP041 | B42: Curly Dock Seed | C42: Rumex crispus | D42: Base | E42: Disturbed Ground | F42: Seed | G42: 8 | H42: 10 | I42: 0 | J42: TAN | K42: 3 | L42: PIG | M42: 2 | P42: 1 | Q42: Astringent | R42: Faint | S42: Dye: rust | T42: 1 | U42: =ROUND(2*T42^2*IF(D42="Rare Active",6,IF(D42="Workhorse",2,1))+(K42+M42+O42)/2,0) -> 5 | V42: 300 | W42: =IF(COUNTIF(Plants!$A$2:$A$1000,C42)>0,"yes","") -> yes
A43: SP042 | B43: Pokeweed Root | C43: Phytolacca americana | D43: Workhorse | E43: Disturbed Ground | F43: Root | G43: 9 | H43: 11 | I43: 9 | J43: SAP | K43: 7 | L43: ANT | M43: 4 | N43: ALK | O43: 3 | P43: 8 | Q43: Acrid | R43: Rank | S43: Potent purge — dangerous | T43: 2 | U43: =ROUND(2*T43^2*IF(D43="Rare Active",6,IF(D43="Workhorse",2,1))+(K43+M43+O43)/2,0) -> 23 | V43: 120 | W43: =IF(COUNTIF(Plants!$A$2:$A$1000,C43)>0,"yes","") -> yes
A44: SP043 | B44: Pokeweed Berry | C44: Phytolacca americana | D44: Base | E44: Disturbed Ground | F44: Fruit | G44: 8 | H44: 10 | I44: 0 | J44: ANT | K44: 7 | P44: 6 | Q44: Bland, then burning | R44: None | S44: Dye: magenta (toxic) | T44: 2 | U44: =ROUND(2*T44^2*IF(D44="Rare Active",6,IF(D44="Workhorse",2,1))+(K44+M44+O44)/2,0) -> 12 | V44: 10 | W44: =IF(COUNTIF(Plants!$A$2:$A$1000,C44)>0,"yes","") -> yes
A45: SP044 | B45: Common Mullein | C45: Verbascum thapsus | D45: Workhorse | E45: Disturbed Ground | F45: Leaf | G45: 6 | H45: 9 | I45: 9 | J45: MUC | K45: 5 | L45: SAP | M45: 2 | P45: 0 | Q45: Fuzzy, bland | R45: Hay | S45: Lung soothe / smoke blend | T45: 1 | U45: =ROUND(2*T45^2*IF(D45="Rare Active",6,IF(D45="Workhorse",2,1))+(K45+M45+O45)/2,0) -> 8 | V45: 45 | W45: =IF(COUNTIF(Plants!$A$2:$A$1000,C45)>0,"yes","") -> yes
A46: SP045 | B46: Mullein Flower | C46: Verbascum thapsus | D46: Base | E46: Disturbed Ground | F46: Flower | G46: 7 | H46: 8 | I46: 0 | J46: MUC | K46: 3 | L46: FLA | M46: 2 | P46: 0 | Q46: Mild | R46: Honey | S46: Ear-oil carrier | T46: 1 | U46: =ROUND(2*T46^2*IF(D46="Rare Active",6,IF(D46="Workhorse",2,1))+(K46+M46+O46)/2,0) -> 5 | V46: 30 | W46: =IF(COUNTIF(Plants!$A$2:$A$1000,C46)>0,"yes","") -> yes
A47: SP046 | B47: Common Yarrow | C47: Achillea millefolium | D47: Workhorse | E47: Prairie | F47: Flower | G47: 6 | H47: 9 | I47: 9 | J47: VOL | K47: 4 | L47: BIT | M47: 3 | N47: FLA | O47: 2 | P47: 1 | Q47: Bitter, camphor | R47: Medicinal | S47: Stop bleeding / fever sweat | T47: 1 | U47: =ROUND(2*T47^2*IF(D47="Rare Active",6,IF(D47="Workhorse",2,1))+(K47+M47+O47)/2,0) -> 9 | V47: 30 | W47: =IF(COUNTIF(Plants!$A$2:$A$1000,C47)>0,"yes","") -> yes
A48: SP047 | B48: Queen Anne's Lace Seed | C48: Daucus carota | D48: Base | E48: Disturbed Ground | F48: Seed | G48: 8 | H48: 10 | I48: 0 | J48: VOL | K48: 3 | P48: 1 | Q48: Carroty-spicy | R48: Carrot | S48: Seed spice | T48: 2 | U48: =ROUND(2*T48^2*IF(D48="Rare Active",6,IF(D48="Workhorse",2,1))+(K48+M48+O48)/2,0) -> 10 | V48: 300 | W48: =IF(COUNTIF(Plants!$A$2:$A$1000,C48)>0,"yes","") -> yes
A49: SP048 | B49: Wild Parsnip | C49: Pastinaca sativa | D49: Base | E49: Disturbed Ground | F49: Root | G49: 10 | H49: 11 | I49: 9 | J49: COU | K49: 6 | L49: SUG | M49: 3 | P49: 5 | Q49: Sweet, then harsh | R49: Parsnip | S49: Sun-burn trap (photo-reactive sap) | T49: 2 | U49: =ROUND(2*T49^2*IF(D49="Rare Active",6,IF(D49="Workhorse",2,1))+(K49+M49+O49)/2,0) -> 13 | V49: 120 | W49: =IF(COUNTIF(Plants!$A$2:$A$1000,C49)>0,"yes","") -> yes
A50: SP049 | B50: Poison Hemlock | C50: Conium maculatum | D50: Workhorse | E50: Riverbank | F50: Seed | G50: 7 | H50: 9 | I50: 0 | J50: ALK | K50: 9 | P50: 10 | Q50: DO NOT TASTE | R50: Mousy | S50: Lethal paralytic — licensed buyers only | T50: 3 | U50: =ROUND(2*T50^2*IF(D50="Rare Active",6,IF(D50="Workhorse",2,1))+(K50+M50+O50)/2,0) -> 41 | V50: 300 | W50: =IF(COUNTIF(Plants!$A$2:$A$1000,C50)>0,"yes","")
A51: SP050 | B51: Water Hemlock | C51: Cicuta maculata | D51: Workhorse | E51: Wetland | F51: Root | G51: 5 | H51: 10 | I51: 0 | J51: RES | K51: 9 | P51: 10 | Q51: DO NOT TASTE | R51: Carrot-like | S51: Lethal convulsant — licensed buyers only | T51: 3 | U51: =ROUND(2*T51^2*IF(D51="Rare Active",6,IF(D51="Workhorse",2,1))+(K51+M51+O51)/2,0) -> 41 | V51: 120 | W51: =IF(COUNTIF(Plants!$A$2:$A$1000,C51)>0,"yes","")
A52: SP051 | B52: Jimsonweed | C52: Datura stramonium | D52: Workhorse | E52: Disturbed Ground | F52: Seed | G52: 8 | H52: 10 | I52: 0 | J52: ALK | K52: 9 | P52: 9 | Q52: DO NOT TASTE | R52: Rank | S52: Delirium; night-sight brews at a razor margin | T52: 2 | U52: =ROUND(2*T52^2*IF(D52="Rare Active",6,IF(D52="Workhorse",2,1))+(K52+M52+O52)/2,0) -> 21 | V52: 300 | W52: =IF(COUNTIF(Plants!$A$2:$A$1000,C52)>0,"yes","") -> yes
A53: SP052 | B53: Common Milkweed | C53: Asclepias syriaca | D53: Base | E53: Prairie | F53: Seed | G53: 9 | H53: 10 | I53: 0 | J53: LAT | K53: 4 | L53: GLY | M53: 3 | P53: 4 | Q53: Bitter | R53: Faint | S53: Floss fiber / insulation | T53: 2 | U53: =ROUND(2*T53^2*IF(D53="Rare Active",6,IF(D53="Workhorse",2,1))+(K53+M53+O53)/2,0) -> 12 | V53: 300 | W53: =IF(COUNTIF(Plants!$A$2:$A$1000,C53)>0,"yes","") -> yes
A54: SP053 | B54: Butterfly Weed | C54: Asclepias tuberosa | D54: Workhorse | E54: Prairie | F54: Root | G54: 9 | H54: 10 | I54: 9 | J54: GLY | K54: 5 | L54: RES | M54: 2 | P54: 3 | Q54: Bitter | R54: Earthy | S54: Pleurisy root — chest | T54: 4 | U54: =ROUND(2*T54^2*IF(D54="Rare Active",6,IF(D54="Workhorse",2,1))+(K54+M54+O54)/2,0) -> 68 | V54: 120 | W54: =IF(COUNTIF(Plants!$A$2:$A$1000,C54)>0,"yes","") -> yes
A55: SP054 | B55: Purple Coneflower | C55: Echinacea purpurea | D55: Workhorse | E55: Prairie | F55: Root | G55: 9 | H55: 10 | I55: 9 | J55: ALK | K55: 3 | L55: FLA | M55: 3 | N55: RES | O55: 2 | P55: 0 | Q55: Tingling, numbing | R55: Earthy | S55: Ward illness (tongue-tingle is the quality test) | T55: 3 | U55: =ROUND(2*T55^2*IF(D55="Rare Active",6,IF(D55="Workhorse",2,1))+(K55+M55+O55)/2,0) -> 40 | V55: 120 | W55: =IF(COUNTIF(Plants!$A$2:$A$1000,C55)>0,"yes","") -> yes
A56: SP055 | B56: Pale Purple Coneflower | C56: Echinacea pallida | D56: Workhorse | E56: Prairie | F56: Root | G56: 9 | H56: 10 | I56: 9 | J56: ALK | K56: 4 | L56: RES | M56: 2 | P56: 0 | Q56: Strong tingle | R56: Earthy | S56: Stronger ward | T56: 4 | U56: =ROUND(2*T56^2*IF(D56="Rare Active",6,IF(D56="Workhorse",2,1))+(K56+M56+O56)/2,0) -> 67 | V56: 120 | W56: =IF(COUNTIF(Plants!$A$2:$A$1000,C56)>0,"yes","")
A57: SP056 | B57: Wild Bergamot | C57: Monarda fistulosa | D57: Workhorse | E57: Prairie | F57: Leaf | G57: 6 | H57: 8 | I57: 9 | J57: VOL | K57: 6 | P57: 0 | Q57: Oregano-hot | R57: Thyme-mint | S57: Antiseptic steam | T57: 1 | U57: =ROUND(2*T57^2*IF(D57="Rare Active",6,IF(D57="Workhorse",2,1))+(K57+M57+O57)/2,0) -> 7 | V57: 45 | W57: =IF(COUNTIF(Plants!$A$2:$A$1000,C57)>0,"yes","") -> yes
A58: SP057 | B58: Virginia Mountain Mint | C58: Pycnanthemum virginianum | D58: Base | E58: Prairie | F58: Leaf | G58: 6 | H58: 9 | I58: 9 | J58: VOL | K58: 5 | P58: 0 | Q58: Cooling | R58: Strong mint | S58: Flavor mask (mint) | T58: 1 | U58: =ROUND(2*T58^2*IF(D58="Rare Active",6,IF(D58="Workhorse",2,1))+(K58+M58+O58)/2,0) -> 5 | V58: 45 | W58: =IF(COUNTIF(Plants!$A$2:$A$1000,C58)>0,"yes","") -> yes
A59: SP058 | B59: Anise Hyssop | C59: Agastache foeniculum | D59: Base | E59: Prairie | F59: Leaf | G59: 6 | H59: 9 | I59: 9 | J59: VOL | K59: 4 | L59: SUG | M59: 1 | P59: 0 | Q59: Licorice | R59: Anise | S59: Flavor mask (licorice) | T59: 1 | U59: =ROUND(2*T59^2*IF(D59="Rare Active",6,IF(D59="Workhorse",2,1))+(K59+M59+O59)/2,0) -> 5 | V59: 45 | W59: =IF(COUNTIF(Plants!$A$2:$A$1000,C59)>0,"yes","")
A60: SP059 | B60: Wild Ginger | C60: Asarum canadense | D60: Workhorse | E60: Upland Forest | F60: Rhizome | G60: 4 | H60: 10 | I60: 6 | J60: VOL | K60: 5 | L60: ACI | M60: 3 | P60: 4 | Q60: Gingery-hot | R60: Spicy | S60: Warming / digestion — kidney strain if overused | T60: 3 | U60: =ROUND(2*T60^2*IF(D60="Rare Active",6,IF(D60="Workhorse",2,1))+(K60+M60+O60)/2,0) -> 40 | V60: 120 | W60: =IF(COUNTIF(Plants!$A$2:$A$1000,C60)>0,"yes","")
A61: SP060 | B61: Mayapple Rhizome | C61: Podophyllum peltatum | D61: Workhorse | E61: Upland Forest | F61: Rhizome | G61: 9 | H61: 10 | I61: 7 | J61: RES | K61: 8 | P61: 9 | Q61: DO NOT TASTE | R61: Faint | S61: Caustic — wart removal only | T61: 3 | U61: =ROUND(2*T61^2*IF(D61="Rare Active",6,IF(D61="Workhorse",2,1))+(K61+M61+O61)/2,0) -> 40 | V61: 120 | W61: =IF(COUNTIF(Plants!$A$2:$A$1000,C61)>0,"yes","") -> yes
A62: SP061 | B62: Mayapple Fruit | C62: Podophyllum peltatum | D62: Base | E62: Upland Forest | F62: Fruit | G62: 7 | H62: 8 | I62: 0 | J62: SUG | K62: 4 | P62: 1 | Q62: Tropical | R62: Lemon | S62: Treat (ripe only — unripe is toxic) | T62: 3 | U62: =ROUND(2*T62^2*IF(D62="Rare Active",6,IF(D62="Workhorse",2,1))+(K62+M62+O62)/2,0) -> 20 | V62: 10 | W62: =IF(COUNTIF(Plants!$A$2:$A$1000,C62)>0,"yes","") -> yes
A63: SP062 | B63: Bloodroot | C63: Sanguinaria canadensis | D63: Rare Active | E63: Upland Forest | F63: Rhizome | G63: 3 | H63: 4 | I63: 5 | J63: ALK | K63: 8 | L63: PIG | M63: 7 | P63: 7 | Q63: Burning | R63: Earthy | S63: Red dye; escharotic; ritual-prepped 'Truthpaint' reveals lies | T63: 4 | U63: =ROUND(2*T63^2*IF(D63="Rare Active",6,IF(D63="Workhorse",2,1))+(K63+M63+O63)/2,0) -> 200 | V63: 120 | W63: =IF(COUNTIF(Plants!$A$2:$A$1000,C63)>0,"yes","")
A64: SP063 | B64: Goldenseal | C64: Hydrastis canadensis | D64: Rare Active | E64: Upland Forest | F64: Rhizome | G64: 9 | H64: 10 | I64: 7 | J64: ALK | K64: 8 | L64: BIT | M64: 6 | N64: PIG | O64: 5 | P64: 3 | Q64: Intensely bitter | R64: Musty | S64: Strongest anti-infective; patches crash if overharvested | T64: 5 | U64: =ROUND(2*T64^2*IF(D64="Rare Active",6,IF(D64="Workhorse",2,1))+(K64+M64+O64)/2,0) -> 310 | V64: 120 | W64: =IF(COUNTIF(Plants!$A$2:$A$1000,C64)>0,"yes","")
A65: SP064 | B65: American Ginseng | C65: Panax quinquefolius | D65: Rare Active | E65: Upland Forest | F65: Root | G65: 9 | H65: 10 | I65: 9 | J65: SAP | K65: 8 | L65: GLY | M65: 3 | P65: 0 | Q65: Bittersweet | R65: Earthy | S65: Stamina — potency scales with root age (count the neck scars) | T65: 5 | U65: =ROUND(2*T65^2*IF(D65="Rare Active",6,IF(D65="Workhorse",2,1))+(K65+M65+O65)/2,0) -> 306 | V65: 120 | W65: =IF(COUNTIF(Plants!$A$2:$A$1000,C65)>0,"yes","")
A66: SP065 | B66: Black Cohosh | C66: Actaea racemosa | D66: Workhorse | E66: Upland Forest | F66: Root | G66: 9 | H66: 10 | I66: 9 | J66: GLY | K66: 5 | L66: RES | M66: 3 | P66: 2 | Q66: Bitter, acrid | R66: Rank | S66: Muscle relaxant | T66: 4 | U66: =ROUND(2*T66^2*IF(D66="Rare Active",6,IF(D66="Workhorse",2,1))+(K66+M66+O66)/2,0) -> 68 | V66: 120 | W66: =IF(COUNTIF(Plants!$A$2:$A$1000,C66)>0,"yes","")
A67: SP066 | B67: Blue Cohosh | C67: Caulophyllum thalictroides | D67: Workhorse | E67: Upland Forest | F67: Root | G67: 9 | H67: 10 | I67: 8 | J67: SAP | K67: 5 | L67: ALK | M67: 4 | P67: 5 | Q67: Acrid | R67: Faint | S67: Uterine — expert-only orders | T67: 4 | U67: =ROUND(2*T67^2*IF(D67="Rare Active",6,IF(D67="Workhorse",2,1))+(K67+M67+O67)/2,0) -> 69 | V67: 120 | W67: =IF(COUNTIF(Plants!$A$2:$A$1000,C67)>0,"yes","")
A68: SP067 | B68: Solomon's Seal | C68: Polygonatum biflorum | D68: Workhorse | E68: Upland Forest | F68: Rhizome | G68: 9 | H68: 10 | I68: 9 | J68: MUC | K68: 6 | L68: SAP | M68: 2 | P68: 1 | Q68: Sweet, slick | R68: Faint | S68: Joint & tendon repair | T68: 3 | U68: =ROUND(2*T68^2*IF(D68="Rare Active",6,IF(D68="Workhorse",2,1))+(K68+M68+O68)/2,0) -> 40 | V68: 120 | W68: =IF(COUNTIF(Plants!$A$2:$A$1000,C68)>0,"yes","")
A69: SP068 | B69: Prairie Trillium | C69: Trillium recurvatum | D69: Workhorse | E69: Upland Forest | F69: Rhizome | G69: 4 | H69: 5 | I69: 6 | J69: SAP | K69: 4 | P69: 2 | Q69: Acrid | R69: Faint | S69: Birthroot — 7 seasons to regrow | T69: 5 | U69: =ROUND(2*T69^2*IF(D69="Rare Active",6,IF(D69="Workhorse",2,1))+(K69+M69+O69)/2,0) -> 102 | V69: 120 | W69: =IF(COUNTIF(Plants!$A$2:$A$1000,C69)>0,"yes","")
A70: SP069 | B70: Spring Beauty | C70: Claytonia virginica | D70: Base | E70: Upland Forest | F70: Root | G70: 3 | H70: 4 | I70: 5 | J70: SUG | K70: 3 | P70: 0 | Q70: Chestnut | R70: Faint | S70: Food | T70: 2 | U70: =ROUND(2*T70^2*IF(D70="Rare Active",6,IF(D70="Workhorse",2,1))+(K70+M70+O70)/2,0) -> 10 | V70: 120 | W70: =IF(COUNTIF(Plants!$A$2:$A$1000,C70)>0,"yes","")
A71: SP070 | B71: Dutchman's Breeches | C71: Dicentra cucullaria | D71: Base | E71: Upland Forest | F71: Root | G71: 3 | H71: 4 | I71: 5 | J71: ALK | K71: 4 | P71: 5 | Q71: Bitter | R71: Faint | S71: Mild sedative — toxic | T71: 3 | U71: =ROUND(2*T71^2*IF(D71="Rare Active",6,IF(D71="Workhorse",2,1))+(K71+M71+O71)/2,0) -> 20 | V71: 120 | W71: =IF(COUNTIF(Plants!$A$2:$A$1000,C71)>0,"yes","")
A72: SP071 | B72: Cutleaf Toothwort | C72: Cardamine concatenata | D72: Base | E72: Upland Forest | F72: Root | G72: 3 | H72: 4 | I72: 5 | J72: GLY | K72: 2 | P72: 0 | Q72: Peppery horseradish | R72: Pungent | S72: Flavor (heat) | T72: 2 | U72: =ROUND(2*T72^2*IF(D72="Rare Active",6,IF(D72="Workhorse",2,1))+(K72+M72+O72)/2,0) -> 9 | V72: 120 | W72: =IF(COUNTIF(Plants!$A$2:$A$1000,C72)>0,"yes","")
A73: SP072 | B73: Ramps | C73: Allium tricoccum | D73: Workhorse | E73: Upland Forest | F73: Bulb | G73: 4 | H73: 5 | I73: 7 | J73: GLY | K73: 4 | L73: SUG | M73: 2 | P73: 0 | Q73: Garlic-onion | R73: Garlic | S73: Ward vermin / circulation | T73: 4 | U73: =ROUND(2*T73^2*IF(D73="Rare Active",6,IF(D73="Workhorse",2,1))+(K73+M73+O73)/2,0) -> 67 | V73: 60 | W73: =IF(COUNTIF(Plants!$A$2:$A$1000,C73)>0,"yes","")
A74: SP073 | B74: Wild Garlic | C74: Allium canadense | D74: Base | E74: Prairie | F74: Bulb | G74: 4 | H74: 6 | I74: 7 | J74: GLY | K74: 3 | P74: 0 | Q74: Garlic | R74: Garlic | S74: Flavor / antimicrobial | T74: 1 | U74: =ROUND(2*T74^2*IF(D74="Rare Active",6,IF(D74="Workhorse",2,1))+(K74+M74+O74)/2,0) -> 4 | V74: 60 | W74: =IF(COUNTIF(Plants!$A$2:$A$1000,C74)>0,"yes","") -> yes
A75: SP074 | B75: Garlic Mustard | C75: Alliaria petiolata | D75: Base | E75: Upland Forest | F75: Leaf | G75: 3 | H75: 6 | I75: 6 | J75: GLY | K75: 3 | P75: 0 | Q75: Garlic-bitter | R75: Garlic | S75: Invasive (reputation bonus for culling) | T75: 1 | U75: =ROUND(2*T75^2*IF(D75="Rare Active",6,IF(D75="Workhorse",2,1))+(K75+M75+O75)/2,0) -> 4 | V75: 45 | W75: =IF(COUNTIF(Plants!$A$2:$A$1000,C75)>0,"yes","") -> yes
A76: SP075 | B76: Sassafras Root Bark | C76: Sassafras albidum | D76: Workhorse | E76: Oak Savanna | F76: Bark | G76: 10 | H76: 3 | I76: 9 | J76: VOL | K76: 7 | P76: 4 | Q76: Root beer | R76: Root beer | S76: Flavor / blood tonic — chronic toxicity | T76: 3 | U76: =ROUND(2*T76^2*IF(D76="Rare Active",6,IF(D76="Workhorse",2,1))+(K76+M76+O76)/2,0) -> 40 | V76: 240 | W76: =IF(COUNTIF(Plants!$A$2:$A$1000,C76)>0,"yes","") -> yes
A77: SP076 | B77: Spicebush Twig | C77: Lindera benzoin | D77: Workhorse | E77: Bottomland Forest | F77: Twig | G77: 1 | H77: 12 | I77: 9 | J77: VOL | K77: 5 | P77: 0 | Q77: Allspice | R77: Citrus-spice | S77: Fever / warming | T77: 3 | U77: =ROUND(2*T77^2*IF(D77="Rare Active",6,IF(D77="Workhorse",2,1))+(K77+M77+O77)/2,0) -> 39 | V77: 200 | W77: =IF(COUNTIF(Plants!$A$2:$A$1000,C77)>0,"yes","") -> yes
A78: SP077 | B78: Spicebush Berry | C78: Lindera benzoin | D78: Base | E78: Bottomland Forest | F78: Fruit | G78: 9 | H78: 10 | I78: 0 | J78: VOL | K78: 5 | L78: RES | M78: 1 | P78: 0 | Q78: Allspice-pepper | R78: Spicy | S78: Spice | T78: 3 | U78: =ROUND(2*T78^2*IF(D78="Rare Active",6,IF(D78="Workhorse",2,1))+(K78+M78+O78)/2,0) -> 21 | V78: 10 | W78: =IF(COUNTIF(Plants!$A$2:$A$1000,C78)>0,"yes","") -> yes
A79: SP078 | B79: Slippery Elm | C79: Ulmus rubra | D79: Workhorse | E79: Bottomland Forest | F79: Bark | G79: 3 | H79: 5 | I79: 0 | J79: MUC | K79: 9 | P79: 0 | Q79: Slimy, sweet | R79: Maple | S79: Throat & gut coat — premium binder | T79: 4 | U79: =ROUND(2*T79^2*IF(D79="Rare Active",6,IF(D79="Workhorse",2,1))+(K79+M79+O79)/2,0) -> 69 | V79: 240 | W79: =IF(COUNTIF(Plants!$A$2:$A$1000,C79)>0,"yes","")
A80: SP079 | B80: Black Willow Bark | C80: Salix nigra | D80: Workhorse | E80: Riverbank | F80: Bark | G80: 3 | H80: 5 | I80: 0 | J80: GLY | K80: 6 | L80: TAN | M80: 4 | P80: 1 | Q80: Bitter | R80: Woody | S80: Pain & fever | T80: 2 | U80: =ROUND(2*T80^2*IF(D80="Rare Active",6,IF(D80="Workhorse",2,1))+(K80+M80+O80)/2,0) -> 21 | V80: 240 | W80: =IF(COUNTIF(Plants!$A$2:$A$1000,C80)>0,"yes","")
A81: SP080 | B81: Wild Cherry Bark | C81: Prunus serotina | D81: Workhorse | E81: Oak Savanna | F81: Bark | G81: 9 | H81: 11 | I81: 8 | J81: GLY | K81: 6 | L81: TAN | M81: 2 | P81: 5 | Q81: Bitter almond | R81: Almond | S81: Cough sedative — cyanogenic | T81: 3 | U81: =ROUND(2*T81^2*IF(D81="Rare Active",6,IF(D81="Workhorse",2,1))+(K81+M81+O81)/2,0) -> 40 | V81: 240 | W81: =IF(COUNTIF(Plants!$A$2:$A$1000,C81)>0,"yes","") -> yes
A82: SP081 | B82: Wild Cherry Fruit | C82: Prunus serotina | D82: Base | E82: Oak Savanna | F82: Fruit | G82: 8 | H82: 9 | I82: 0 | J82: SUG | K82: 4 | L82: ANT | M82: 3 | P82: 1 | Q82: Bittersweet | R82: Cherry | S82: Cordial base | T82: 3 | U82: =ROUND(2*T82^2*IF(D82="Rare Active",6,IF(D82="Workhorse",2,1))+(K82+M82+O82)/2,0) -> 22 | V82: 10 | W82: =IF(COUNTIF(Plants!$A$2:$A$1000,C82)>0,"yes","") -> yes
A83: SP082 | B83: Witch Hazel | C83: Hamamelis virginiana | D83: Workhorse | E83: Upland Forest | F83: Bark | G83: 10 | H83: 12 | I83: 10 | J83: TAN | K83: 7 | P83: 0 | Q83: Astringent | R83: Faint | S83: Astringent wash | T83: 3 | U83: =ROUND(2*T83^2*IF(D83="Rare Active",6,IF(D83="Workhorse",2,1))+(K83+M83+O83)/2,0) -> 40 | V83: 240 | W83: =IF(COUNTIF(Plants!$A$2:$A$1000,C83)>0,"yes","")
A84: SP083 | B84: Staghorn Sumac Berry | C84: Rhus typhina | D84: Base | E84: Oak Savanna | F84: Fruit | G84: 8 | H84: 10 | I84: 0 | J84: ACI | K84: 6 | L84: TAN | M84: 4 | P84: 0 | Q84: Lemony | R84: Tart | S84: Acidifier / dye | T84: 2 | U84: =ROUND(2*T84^2*IF(D84="Rare Active",6,IF(D84="Workhorse",2,1))+(K84+M84+O84)/2,0) -> 13 | V84: 10 | W84: =IF(COUNTIF(Plants!$A$2:$A$1000,C84)>0,"yes","")
A85: SP084 | B85: Smooth Sumac Leaf | C85: Rhus glabra | D85: Base | E85: Prairie | F85: Leaf | G85: 9 | H85: 10 | I85: 0 | J85: TAN | K85: 7 | L85: PIG | M85: 3 | P85: 0 | Q85: Astringent | R85: Faint | S85: Tanning | T85: 2 | U85: =ROUND(2*T85^2*IF(D85="Rare Active",6,IF(D85="Workhorse",2,1))+(K85+M85+O85)/2,0) -> 13 | V85: 45 | W85: =IF(COUNTIF(Plants!$A$2:$A$1000,C85)>0,"yes","") -> yes
A86: SP085 | B86: Poison Ivy | C86: Toxicodendron radicans | D86: Base | E86: Bottomland Forest | F86: Leaf | G86: 5 | H86: 9 | I86: 0 | J86: RES | K86: 8 | P86: 7 | Q86: NEVER HANDLE BARE | R86: None | S86: Contaminant — ruins any batch it touches | T86: 1 | U86: =ROUND(2*T86^2*IF(D86="Rare Active",6,IF(D86="Workhorse",2,1))+(K86+M86+O86)/2,0) -> 6 | V86: 45 | W86: =IF(COUNTIF(Plants!$A$2:$A$1000,C86)>0,"yes","") -> yes
A87: SP086 | B87: Elderberry | C87: Sambucus canadensis | D87: Workhorse | E87: Riverbank | F87: Fruit | G87: 8 | H87: 9 | I87: 9 | J87: ANT | K87: 6 | L87: FLA | M87: 4 | P87: 2 | Q87: Tart | R87: Musky | S87: Immunity syrup — must be cooked | T87: 2 | U87: =ROUND(2*T87^2*IF(D87="Rare Active",6,IF(D87="Workhorse",2,1))+(K87+M87+O87)/2,0) -> 21 | V87: 10 | W87: =IF(COUNTIF(Plants!$A$2:$A$1000,C87)>0,"yes","") -> yes
A88: SP087 | B88: Elderflower | C88: Sambucus canadensis | D88: Workhorse | E88: Riverbank | F88: Flower | G88: 6 | H88: 7 | I88: 0 | J88: FLA | K88: 5 | L88: VOL | M88: 2 | P88: 0 | Q88: Floral | R88: Muscat | S88: Fever sweat / cordial | T88: 2 | U88: =ROUND(2*T88^2*IF(D88="Rare Active",6,IF(D88="Workhorse",2,1))+(K88+M88+O88)/2,0) -> 20 | V88: 30 | W88: =IF(COUNTIF(Plants!$A$2:$A$1000,C88)>0,"yes","") -> yes
A89: SP088 | B89: Downy Hawthorn | C89: Crataegus mollis | D89: Workhorse | E89: Oak Savanna | F89: Fruit | G89: 9 | H89: 10 | I89: 10 | J89: FLA | K89: 6 | L89: ACI | M89: 2 | P89: 0 | Q89: Mealy, tart | R89: Apple | S89: Heart tonic | T89: 3 | U89: =ROUND(2*T89^2*IF(D89="Rare Active",6,IF(D89="Workhorse",2,1))+(K89+M89+O89)/2,0) -> 40 | V89: 10 | W89: =IF(COUNTIF(Plants!$A$2:$A$1000,C89)>0,"yes","") -> yes
A90: SP089 | B90: Pasture Rose Hip | C90: Rosa carolina | D90: Workhorse | E90: Prairie | F90: Fruit | G90: 9 | H90: 12 | I90: 10 | J90: ACI | K90: 5 | L90: FLA | M90: 3 | N90: SUG | O90: 2 | P90: 0 | Q90: Tart | R90: Fruity | S90: Vitality / scurvy cure | T90: 2 | U90: =ROUND(2*T90^2*IF(D90="Rare Active",6,IF(D90="Workhorse",2,1))+(K90+M90+O90)/2,0) -> 21 | V90: 10 | W90: =IF(COUNTIF(Plants!$A$2:$A$1000,C90)>0,"yes","") -> yes
A91: SP090 | B91: Pasture Rose Petal | C91: Rosa carolina | D91: Base | E91: Prairie | F91: Flower | G91: 6 | H91: 7 | I91: 0 | J91: VOL | K91: 3 | L91: TAN | M91: 2 | P91: 0 | Q91: Floral | R91: Rose | S91: Perfume / flavor | T91: 2 | U91: =ROUND(2*T91^2*IF(D91="Rare Active",6,IF(D91="Workhorse",2,1))+(K91+M91+O91)/2,0) -> 11 | V91: 30 | W91: =IF(COUNTIF(Plants!$A$2:$A$1000,C91)>0,"yes","") -> yes
A92: SP091 | B92: Basswood Flower | C92: Tilia americana | D92: Workhorse | E92: Upland Forest | F92: Flower | G92: 6 | H92: 7 | I92: 0 | J92: MUC | K92: 4 | L92: VOL | M92: 2 | N92: FLA | O92: 2 | P92: 0 | Q92: Honeyed | R92: Linden | S92: Calm / sleep | T92: 3 | U92: =ROUND(2*T92^2*IF(D92="Rare Active",6,IF(D92="Workhorse",2,1))+(K92+M92+O92)/2,0) -> 40 | V92: 30 | W92: =IF(COUNTIF(Plants!$A$2:$A$1000,C92)>0,"yes","")
A93: SP092 | B93: Catnip | C93: Nepeta cataria | D93: Workhorse | E93: Old Homestead | F93: Leaf | G93: 6 | H93: 9 | I93: 9 | J93: VOL | K93: 5 | P93: 0 | Q93: Minty-bitter | R93: Mint-musk | S93: Calm (humans) / chaos (cats) | T93: 1 | U93: =ROUND(2*T93^2*IF(D93="Rare Active",6,IF(D93="Workhorse",2,1))+(K93+M93+O93)/2,0) -> 7 | V93: 45 | W93: =IF(COUNTIF(Plants!$A$2:$A$1000,C93)>0,"yes","") -> yes
A94: SP093 | B94: Motherwort | C94: Leonurus cardiaca | D94: Workhorse | E94: Old Homestead | F94: Leaf | G94: 6 | H94: 8 | I94: 9 | J94: BIT | K94: 6 | L94: ALK | M94: 2 | P94: 0 | Q94: Very bitter | R94: Rank | S94: Anxiety / heart flutter | T94: 1 | U94: =ROUND(2*T94^2*IF(D94="Rare Active",6,IF(D94="Workhorse",2,1))+(K94+M94+O94)/2,0) -> 8 | V94: 45 | W94: =IF(COUNTIF(Plants!$A$2:$A$1000,C94)>0,"yes","") -> yes
A95: SP094 | B95: Self-heal | C95: Prunella vulgaris | D95: Workhorse | E95: Disturbed Ground | F95: Flower | G95: 6 | H95: 9 | I95: 9 | J95: TAN | K95: 3 | L95: FLA | M95: 3 | P95: 0 | Q95: Mild-bitter | R95: Grassy | S95: All-purpose healing (weak, but stacks) | T95: 1 | U95: =ROUND(2*T95^2*IF(D95="Rare Active",6,IF(D95="Workhorse",2,1))+(K95+M95+O95)/2,0) -> 7 | V95: 30 | W95: =IF(COUNTIF(Plants!$A$2:$A$1000,C95)>0,"yes","") -> yes
A96: SP095 | B96: Mad-dog Skullcap | C96: Scutellaria lateriflora | D96: Workhorse | E96: Wetland | F96: Leaf | G96: 7 | H96: 9 | I96: 9 | J96: FLA | K96: 6 | L96: BIT | M96: 3 | P96: 0 | Q96: Bitter | R96: Grassy | S96: Nerve calm | T96: 3 | U96: =ROUND(2*T96^2*IF(D96="Rare Active",6,IF(D96="Workhorse",2,1))+(K96+M96+O96)/2,0) -> 41 | V96: 45 | W96: =IF(COUNTIF(Plants!$A$2:$A$1000,C96)>0,"yes","")
A97: SP096 | B97: Blue Vervain | C97: Verbena hastata | D97: Workhorse | E97: Wetland | F97: Leaf | G97: 7 | H97: 9 | I97: 9 | J97: GLY | K97: 4 | L97: BIT | M97: 6 | P97: 0 | Q97: Extremely bitter | R97: Faint | S97: Tension release | T97: 2 | U97: =ROUND(2*T97^2*IF(D97="Rare Active",6,IF(D97="Workhorse",2,1))+(K97+M97+O97)/2,0) -> 21 | V97: 45 | W97: =IF(COUNTIF(Plants!$A$2:$A$1000,C97)>0,"yes","")
A98: SP097 | B98: Boneset | C98: Eupatorium perfoliatum | D98: Workhorse | E98: Wetland | F98: Leaf | G98: 7 | H98: 9 | I98: 9 | J98: BIT | K98: 7 | L98: GLY | M98: 3 | P98: 1 | Q98: Bitter | R98: Faint | S98: Break fever | T98: 2 | U98: =ROUND(2*T98^2*IF(D98="Rare Active",6,IF(D98="Workhorse",2,1))+(K98+M98+O98)/2,0) -> 21 | V98: 45 | W98: =IF(COUNTIF(Plants!$A$2:$A$1000,C98)>0,"yes","")
A99: SP098 | B99: Joe-Pye Weed | C99: Eutrochium purpureum | D99: Base | E99: Wetland | F99: Root | G99: 9 | H99: 10 | I99: 9 | J99: FLA | K99: 2 | L99: RES | M99: 2 | P99: 1 | Q99: Bitter | R99: Vanilla when dried | S99: Gravel root (kidney) | T99: 2 | U99: =ROUND(2*T99^2*IF(D99="Rare Active",6,IF(D99="Workhorse",2,1))+(K99+M99+O99)/2,0) -> 10 | V99: 120 | W99: =IF(COUNTIF(Plants!$A$2:$A$1000,C99)>0,"yes","")
A100: SP099 | B100: Swamp Milkweed | C100: Asclepias incarnata | D100: Base | E100: Wetland | F100: Seed | G100: 9 | H100: 10 | I100: 0 | J100: LAT | K100: 3 | L100: GLY | M100: 3 | P100: 4 | Q100: Bitter | R100: Faint | S100: Floss / filler | T100: 2 | U100: =ROUND(2*T100^2*IF(D100="Rare Active",6,IF(D100="Workhorse",2,1))+(K100+M100+O100)/2,0) -> 11 | V100: 300 | W100: =IF(COUNTIF(Plants!$A$2:$A$1000,C100)>0,"yes","")
...

Sheet Plants
A1: Latin Name | B1: Plant Name | C1: Maps | D1: Growth Form | E1: Life Cycle | F1: Height (m) | G1: Leaf Color | H1: Flower Color | I1: Dormant Color | J1: Green-up DOY | K1: Flower Start DOY | L1: Flower End DOY | M1: Fruit Ripe DOY | N1: Dieback DOY | O1: Winter Form | P1: Crown | Q1: Light Opt | R1: Light Tol | S1: Moist Opt | T1: Moist Tol | U1: Disturb Opt | V1: Disturb Tol | W1: Fert Opt | X1: Fert Tol | Y1: Mow Tolerance | Z1: C-value | AA1: Origin | AB1: Dispersal | AC1: Patch Scale (m) | AD1: Abundance | AE1: Host | AF1: Flower Shape | AG1: Habitat Notes
A2: Cichorium intybus | B2: Chicory | C2: 1 | D2: tallForb | E2: perennial | F2: 1 | G2: #5d7a3e | H2: #7fa6e6 | I2: #8a7a5e | J2: 75 | K2: 170 | L2: 275 | M2: 220 | N2: 300 | O2: rosette | Q2: 1 | R2: 0.35 | S2: 0.35 | T2: 0.3 | U2: 0.55 | V2: 0.35 | W2: 0.45 | X2: 0.35 | Y2: 2 | Z2: 0 | AA2: introduced | AB2: wind | AC2: 6 | AD2: 0.6 | AE2: soilOrGravel | AF2: daisy | AG2: Gravel shoulders and ditch banks; survives twice-yearly ditch mowing.
A3: Daucus carota | B3: Queen Anne's Lace | C3: 1 | D3: tallForb | E3: biennial | F3: 0.9 | G3: #6f8f45 | H3: #f3f1e6 | I3: #8a7a60 | J3: 70 | K3: 165 | L3: 260 | M3: 230 | N3: 300 | O3: rosette | Q3: 1 | R3: 0.35 | S3: 0.4 | T3: 0.3 | U3: 0.45 | V3: 0.3 | W3: 0.4 | X3: 0.35 | Y3: 2 | Z3: 0 | AA3: introduced | AB3: wind | AC3: 8 | AD3: 0.7 | AE3: soilOrGravel | AF3: umbel | AG3: Roadsides and old fields; first-year plants overwinter as ferny rosettes.
A4: Pastinaca sativa | B4: Wild Parsnip | C4: 1 | D4: tallForb | E4: biennial | F4: 1.3 | G4: #7a9a3c | H4: #d8c23a | I4: #9a8a5a | J4: 75 | K4: 150 | L4: 200 | M4: 205 | N4: 260 | O4: rosette | Q4: 1 | R4: 0.35 | S4: 0.5 | T4: 0.3 | U4: 0.4 | V4: 0.3 | W4: 0.55 | X4: 0.3 | Y4: 2 | Z4: 0 | AA4: introduced | AB4: wind | AC4: 10 | AD4: 0.5 | AE4: soil | AF4: umbel | AG4: Spreads along mowed roadsides; sap causes sun burns.
A5: Dipsacus fullonum | B5: Wild Teasel | C5: 1 | D5: tallForb | E5: biennial | F5: 1.8 | G5: #5f7a3a | H5: #b39ad6 | I5: #9a8768 | J5: 70 | K5: 185 | L5: 230 | M5: 245 | N5: 280 | O5: standing | Q5: 1 | R5: 0.35 | S5: 0.55 | T5: 0.3 | U5: 0.4 | V5: 0.3 | W5: 0.5 | X5: 0.3 | Y5: 1 | Z5: 0 | AA5: invasive | AB5: wind | AC5: 12 | AD5: 0.45 | AE5: soil | AF5: globe | AG5: Colonizes ditches; spiny dead heads stand all winter.
A6: Ambrosia artemisiifolia | B6: Common Ragweed | C6: 1 | D6: forb | E6: summerAnnual | F6: 0.9 | G6: #6b8a3a | H6: #a8a65a | I6: #8a7a5a | J6: 110 | K6: 220 | L6: 275 | M6: 260 | N6: 290 | O6: none | Q6: 1 | R6: 0.35 | S6: 0.4 | T6: 0.3 | U6: 0.75 | V6: 0.3 | W6: 0.5 | X6: 0.35 | Y6: 1 | Z6: 0 | AA6: native | AB6: gravity | AC6: 5 | AD6: 0.6 | AE6: soilOrGravel | AF6: plume | AG6: Annual of freshly turned or scraped soil.
A7: Solanum carolinense | B7: Horse Nettle | C7: 1 | D7: forb | E7: perennial | F7: 0.6 | G7: #6a8a42 | H7: #e6ddf0 | I7: #c8b04a | J7: 120 | K7: 150 | L7: 250 | M7: 240 | N7: 285 | O7: standing | Q7: 1 | R7: 0.35 | S7: 0.4 | T7: 0.3 | U7: 0.6 | V7: 0.35 | W7: 0.45 | X7: 0.35 | Y7: 2 | Z7: 0 | AA7: native | AB7: animal | AC7: 6 | AD7: 0.4 | AE7: soil | AF7: daisy | AG7: Rhizomatous pasture weed; yellow berries hang on dead stems in winter.
A8: Verbascum thapsus | B8: Common Mullein | C8: 1 | D8: tallForb | E8: biennial | F8: 1.6 | G8: #9aa58a | H8: #e8d24a | I8: #6e5a40 | J8: 60 | K8: 170 | L8: 245 | M8: 240 | N8: 300 | O8: rosette | Q8: 1 | R8: 0.3 | S8: 0.3 | T8: 0.3 | U8: 0.55 | V8: 0.3 | W8: 0.35 | X8: 0.3 | Y8: 1 | Z8: 0 | AA8: introduced | AB8: gravity | AC8: 8 | AD8: 0.45 | AE8: soilOrGravel | AF8: spike | AG8: Gravelly, dry, disturbed ground; big woolly rosettes are obvious in March.
A9: Rumex crispus | B9: Curly Dock | C9: 1 | D9: tallForb | E9: perennial | F9: 1 | G9: #5f7d36 | H9: #8a6a3a | I9: #7a4a2a | J9: 55 | K9: 140 | L9: 180 | M9: 190 | N9: 320 | O9: rosette | Q9: 1 | R9: 0.4 | S9: 0.6 | T9: 0.3 | U9: 0.5 | V9: 0.35 | W9: 0.6 | X9: 0.3 | Y9: 2 | Z9: 0 | AA9: introduced | AB9: wind | AC9: 6 | AD9: 0.55 | AE9: soil | AF9: plume | AG9: Moist disturbed ground; rusty seed stalks stand through winter.
A10: Equisetum arvense | B10: Field Horsetail | C10: 1 | D10: horsetail | E10: perennial | F10: 0.35 | G10: #6f9a3c | H10: #c8b48a | I10: #8a7a5a | J10: 75 | K10: 75 | L10: 105 | M10: 105 | N10: 300 | O10: none | Q10: 0.85 | R10: 0.4 | S10: 0.75 | T10: 0.25 | U10: 0.35 | V10: 0.35 | W10: 0.45 | X10: 0.35 | Y10: 2 | Z10: 0 | AA10: native | AB10: rhizome | AC10: 5 | AD10: 0.5 | AE10: soilOrGravel | AF10: spike | AG10: Damp ditch bottoms and wet gravel; tan fertile stems in early spring.
A11: Capsella bursa-pastoris | B11: Shepherd's Purse | C11: 1 | D11: rosette | E11: winterAnnual | F11: 0.3 | G11: #6f8f45 | H11: #f5f5f0 | I11: #8a8a5a | J11: 280 | K11: 60 | L11: 150 | M11: 120 | N11: 170 | O11: rosette | Q11: 1 | R11: 0.4 | S11: 0.45 | T11: 0.35 | U11: 0.65 | V11: 0.35 | W11: 0.55 | X11: 0.35 | Y11: 3 | Z11: 0 | AA11: introduced | AB11: gravity | AC11: 3 | AD11: 0.5 | AE11: soilOrGravel | AF11: spike | AG11: Winter annual of bare, trodden soil.
A12: Taraxacum officinale | B12: Dandelion | C12: 1 | D12: rosette | E12: perennial | F12: 0.25 | G12: #5c8a35 | H12: #f2c81e | I12: #5a6a3a | J12: 50 | K12: 80 | L12: 140 | M12: 110 | N12: 340 | O12: rosette | Q12: 0.95 | R12: 0.4 | S12: 0.5 | T12: 0.35 | U12: 0.4 | V12: 0.35 | W12: 0.55 | X12: 0.35 | Y12: 3 | Z12: 0 | AA12: introduced | AB12: wind | AC12: 4 | AD12: 0.75 | AE12: soil | AF12: daisy | AG12: Lawns and anywhere mowed; outcompeted in tall unmowed grass.
A13: Viola sororia | B13: Common Blue Violet | C13: 1 | D13: rosette | E13: perennial | F13: 0.15 | G13: #3f7a3a | H13: #6a4fc9 | I13: #4a5a3a | J13: 75 | K13: 90 | L13: 125 | M13: 140 | N13: 310 | O13: none | Q13: 0.6 | R13: 0.35 | S13: 0.55 | T13: 0.3 | U13: 0.3 | V13: 0.3 | W13: 0.55 | X13: 0.3 | Y13: 3 | Z13: 1 | AA13: native | AB13: ballistic | AC13: 5 | AD13: 0.6 | AE13: soil | AF13: daisy | AG13: Shady lawn edges and under yard trees.
... A68: Silphium laciniatum | B68: Compass Plant | C68: 1 | D68: tallForb | E68: perennial | F68: 2.2 | G68: #5a7a4a | H68: #f0c030 | I68: #5a4a38 | J68: 105 | K68: 190 | L68: 240 | M68: 260 | N68: 300 | O68: standing | Q68: 1 | R68: 0.25 | S68: 0.4 | T68: 0.3 | U68: 0.03 | V68: 0.15 | W68: 0.3 | X68: 0.25 | Y68: 0 | Z68: 8 | AA68: native | AB68: gravity | AC68: 6 | AD68: 0.25 | AE68: soil | AF68: daisy | AG68: Deep-rooted remnant giant; leaves point north–south.
A69: Sassafras albidum | B69: Sassafras | C69: 1 | D69: tree | E69: woody | F69: 8 | G69: #5a8a3a | H69: #e0d460 | I69: #5a5a3a | J69: 105 | K69: 90 | L69: 110 | M69: 230 | N69: 300 | O69: bare | P69: upright | Q69: 0.85 | R69: 0.4 | S69: 0.4 | T69: 0.3 | U69: 0.15 | V69: 0.25 | W69: 0.4 | X69: 0.3 | Y69: 0 | Z69: 2 | AA69: native | AB69: bird | AC69: 6 | AD69: 0.5 | AE69: soil | AF69: cluster | AG69: Fencerow colonies from root suckers.
A70: Diospyros virginiana | B70: Persimmon | C70: 1 | D70: tree | E70: woody | F70: 10 | G70: #4f7a3a | H70: #e8e4c0 | I70: #3a3a34 | J70: 115 | K70: 140 | L70: 160 | M70: 285 | N70: 310 | O70: bare | P70: upright | Q70: 0.9 | R70: 0.4 | S70: 0.45 | T70: 0.35 | U70: 0.15 | V70: 0.25 | W70: 0.4 | X70: 0.3 | Y70: 0 | Z70: 2 | AA70: native | AB70: animal | AC70: 6 | AD70: 0.35 | AE70: soil | AF70: cluster | AG70: Fencerows and old fields; fruit ripens after frost.
A71: Rubus occidentalis | B71: Black Raspberry | C71: 1 | D71: cane | E71: woody | F71: 1.2 | G71: #4f7a35 | H71: #f5f5ef | I71: #a8a0b8 | J71: 80 | K71: 125 | L71: 145 | M71: 175 | N71: 330 | O71: standing | P71: arching | Q71: 0.75 | R71: 0.35 | S71: 0.5 | T71: 0.3 | U71: 0.25 | V71: 0.3 | W71: 0.55 | X71: 0.3 | Y71: 0 | Z71: 2 | AA71: native | AB71: bird | AC71: 5 | AD71: 0.6 | AE71: soil | AF71: daisy | AG71: Bird-sown at fence lines; waxy purple-white canes in winter.
A72: Rubus allegheniensis | B72: Blackberry | C72: 1 | D72: cane | E72: woody | F72: 1.5 | G72: #3f6a30 | H72: #f5f5ef | I72: #6a2a2a | J72: 85 | K72: 140 | L72: 160 | M72: 200 | N72: 330 | O72: standing | P72: arching | Q72: 0.9 | R72: 0.35 | S72: 0.5 | T72: 0.3 | U72: 0.2 | V72: 0.3 | W72: 0.5 | X72: 0.3 | Y72: 0 | Z72: 2 | AA72: native | AB72: bird | AC72: 7 | AD72: 0.65 | AE72: soil | AF72: daisy | AG72: Thorny thickets in sunny fencerow gaps.
A73: Rhus glabra | B73: Smooth Sumac | C73: 1 | D73: shrub | E73: woody | F73: 3 | G73: #4f7a35 | H73: #d8d8a0 | I73: #8a3a2a | J73: 120 | K73: 160 | L73: 180 | M73: 240 | N73: 285 | O73: bare | P73: vase | Q73: 1 | R73: 0.3 | S73: 0.3 | T73: 0.3 | U73: 0.15 | V73: 0.25 | W73: 0.3 | X73: 0.3 | Y73: 0 | Z73: 1 | AA73: native | AB73: bird | AC73: 10 | AD73: 0.45 | AE73: soil | AF73: plume | AG73: Clonal stands creeping into unmowed fields.
A74: Juniperus virginiana | B74: Eastern Red Cedar | C74: 1 | D74: tree | E74: woody | F74: 9 | G74: #27402a | H74: #6a7a5a | I74: #2e4630 | J74: 1 | K74: 60 | L74: 90 | M74: 300 | N74: 999 | O74: evergreen | P74: conifer | Q74: 0.95 | R74: 0.4 | S74: 0.3 | T74: 0.35 | U74: 0.15 | V74: 0.25 | W74: 0.35 | X74: 0.3 | Y74: 0 | Z74: 0 | AA74: native | AB74: bird | AC74: 6 | AD74: 0.85 | AE74: soil | AF74: cluster | AG74: Bird-planted along every fence; invades prairie that isn't burned.
A75: Rosa carolina | B75: Pasture Rose | C75: 1 | D75: cane | E75: woody | F75: 0.7 | G75: #4f7a35 | H75: #e8a0b8 | I75: #8a3a30 | J75: 100 | K75: 140 | L75: 170 | M75: 250 | N75: 310 | O75: standing | P75: arching | Q75: 0.9 | R75: 0.35 | S75: 0.4 | T75: 0.3 | U75: 0.1 | V75: 0.25 | W75: 0.35 | X75: 0.3 | Y75: 0 | Z75: 4 | AA75: native | AB75: bird | AC75: 5 | AD75: 0.35 | AE75: soil | AF75: daisy | AG75: Low thorny clumps in old fencerows; red hips in winter.
A76: Toxicodendron radicans | B76: Poison Ivy | C76: 1 | D76: vine | E76: woody | F76: 0.8 | G76: #3f6a30 | H76: #e0e0b0 | I76: #6a5a48 | J76: 105 | K76: 135 | L76: 150 | M76: 250 | N76: 290 | O76: standing | Q76: 0.6 | R76: 0.4 | S76: 0.5 | T76: 0.35 | U76: 0.2 | V76: 0.3 | W76: 0.55 | X76: 0.3 | Y76: 0 | Z76: 1 | AA76: native | AB76: bird | AC76: 6 | AD76: 0.55 | AE76: soil | AF76: cluster | AG76: Climbs fence posts and trees where birds drop seed.
A77: Parthenocissus quinquefolia | B77: Virginia Creeper | C77: 1 | D77: vine | E77: woody | F77: 0.6 | G77: #4f7a35 | H77: #c8d0a0 | I77: #5a4a3a | J77: 105 | K77: 160 | L77: 180 | M77: 255 | N77: 290 | O77: none | Q77: 0.55 | R77: 0.4 | S77: 0.5 | T77: 0.3 | U77: 0.2 | V77: 0.3 | W77: 0.55 | X77: 0.3 | Y77: 0 | Z77: 2 | AA77: native | AB77: bird | AC77: 6 | AD77: 0.45 | AE77: soil | AF77: cluster | AG77: Five-leaflet vine on fencerow trees; looks like grape until you count.
A78: Vitis riparia | B78: Riverbank Grape | C78: 1 | D78: vine | E78: woody | F78: 1.2 | G78: #5a8a3a | H78: #d8dca0 | I78: #6a4a30 | J78: 105 | K78: 140 | L78: 155 | M78: 245 | N78: 295 | O78: standing | Q78: 0.8 | R78: 0.4 | S78: 0.6 | T78: 0.3 | U78: 0.2 | V78: 0.3 | W78: 0.55 | X78: 0.3 | Y78: 0 | Z78: 2 | AA78: native | AB78: bird | AC78: 7 | AD78: 0.45 | AE78: soil | AF78: cluster | AG78: Shreddy-barked tangles over fencerow shrubs.
A79: Prunus serotina | B79: Wild Cherry | C79: 1 | D79: tree | E79: woody | F79: 10 | G79: #3f6a30 | H79: #f5f5ef | I79: #3a3430 | J79: 100 | K79: 115 | L79: 130 | M79: 205 | N79: 295 | O79: bare | P79: upright | Q79: 0.85 | R79: 0.4 | S79: 0.45 | T79: 0.3 | U79: 0.15 | V79: 0.25 | W79: 0.5 | X79: 0.3 | Y79: 0 | Z79: 1 | AA79: native | AB79: bird | AC79: 6 | AD79: 0.55 | AE79: soil | AF79: cluster | AG79: The commonest bird-planted fencerow tree.
A80: Crataegus mollis | B80: Downy Hawthorn | C80: 1 | D80: tree | E80: woody | F80: 6 | G80: #4f7a35 | H80: #f5f5ef | I80: #4a4038 | J80: 95 | K80: 110 | L80: 125 | M80: 260 | N80: 300 | O80: bare | P80: spreading | Q80: 0.9 | R80: 0.35 | S80: 0.5 | T80: 0.3 | U80: 0.15 | V80: 0.25 | W80: 0.45 | X80: 0.3 | Y80: 0 | Z80: 3 | AA80: native | AB80: bird | AC80: 5 | AD80: 0.4 | AE80: soil | AF80: globe | AG80: Thorny small tree of old pastures and fences.
A81: Morus rubra | B81: Red Mulberry | C81: 1 | D81: tree | E81: woody | F81: 9 | G81: #4f7a35 | H81: #c8d0a0 | I81: #4a4038 | J81: 105 | K81: 105 | L81: 120 | M81: 165 | N81: 300 | O81: bare | P81: spreading | Q81: 0.7 | R81: 0.4 | S81: 0.55 | T81: 0.3 | U81: 0.15 | V81: 0.25 | W81: 0.6 | X81: 0.3 | Y81: 0 | Z81: 5 | AA81: native | AB81: bird | AC81: 5 | AD81: 0.3 | AE81: soil | AF81: cluster | AG81: Fencerow and woods-edge tree; fruit in June.
A82: Juglans nigra | B82: Black Walnut | C82: 1 | D82: tree | E82: woody | F82: 15 | G82: #5a8a3a | H82: #a8b070 | I82: #2e2a26 | J82: 125 | K82: 125 | L82: 140 | M82: 265 | N82: 285 | O82: bare | P82: spreading | Q82: 0.8 | R82: 0.4 | S82: 0.6 | T82: 0.3 | U82: 0.1 | V82: 0.25 | W82: 0.7 | X82: 0.3 | Y82: 0 | Z82: 4 | AA82: native | AB82: caching | AC82: 8 | AD82: 0.45 | AE82: soil | AF82: cluster | AG82: Rich edge soil; squirrels plant the nuts.
A83: Carya ovata | B83: Shagbark Hickory | C83: 1 | D83: tree | E83: woody | F83: 18 | G83: #4f7a35 | H83: #a8b070 | I83: #5a5048 | J83: 110 | K83: 120 | L83: 135 | M83: 275 | N83: 295 | O83: bare | P83: upright | Q83: 0.6 | R83: 0.4 | S83: 0.45 | T83: 0.3 | U83: 0.05 | V83: 0.2 | W83: 0.5 | X83: 0.3 | Y83: 0 | Z83: 4 | AA83: native | AB83: caching | AC83: 8 | AD83: 0.45 | AE83: soil | AF83: cluster | AG83: Upland woods edge; shaggy bark plates.
A84: Quercus alba | B84: White Oak | C84: 1 | D84: tree | E84: woody | F84: 18 | G84: #4f7a35 | H84: #c8c070 | I84: #8a8478 | J84: 110 | K84: 105 | L84: 120 | M84: 270 | N84: 305 | O84: bare | P84: spreading | Q84: 0.6 | R84: 0.4 | S84: 0.4 | T84: 0.3 | U84: 0.05 | V84: 0.2 | W84: 0.45 | X84: 0.3 | Y84: 0 | Z84: 5 | AA84: native | AB84: caching | AC84: 10 | AD84: 0.55 | AE84: soil | AF84: cluster | AG84: The dominant upland tree behind the field.
A85: Acer saccharum | B85: Sugar Maple | C85: 1 | D85: tree | E85: woody | F85: 20 | G85: #4f7a35 | H85: #c8c060 | I85: #4a4440 | J85: 100 | K85: 75 | L85: 95 | M85: 160 | N85: 300 | O85: bare | P85: upright | Q85: 0.4 | R85: 0.4 | S85: 0.5 | T85: 0.3 | U85: 0.05 | V85: 0.2 | W85: 0.6 | X85: 0.3 | Y85: 0 | Z85: 5 | AA85: native | AB85: wind | AC85: 10 | AD85: 0.4 | AE85: soil | AF85: plume | AG85: Shade-tolerant upland tree; tapped for sap in late winter.
A86: Lindera benzoin | B86: Spicebush | C86: 1 | D86: shrub | E86: woody | F86: 2.5 | G86: #4f7a35 | H86: #e8d040 | I86: #5a5040 | J86: 105 | K86: 64 | L86: 98 | M86: 255 | N86: 295 | O86: bare | P86: multistem | Q86: 0.35 | R86: 0.3 | S86: 0.65 | T86: 0.25 | U86: 0.05 | V86: 0.2 | W86: 0.65 | X86: 0.3 | Y86: 0 | Z86: 7 | AA86: native | AB86: bird | AC86: 6 | AD86: 0.55 | AE86: soil | AF86: cluster | AG86: Moist woods edge; yellow bloom on bare twigs in March.
A87: Lonicera maackii | B87: Bush Honeysuckle | C87: 1 | D87: shrub | E87: woody | F87: 4 | G87: #4f8a3a | H87: #f5f2e2 | I87: #4a5a38 | J87: 60 | K87: 125 | L87: 145 | M87: 290 | N87: 330 | O87: bare | P87: multistem | Q87: 0.45 | R87: 0.45 | S87: 0.5 | T87: 0.3 | U87: 0.2 | V87: 0.3 | W87: 0.6 | X87: 0.3 | Y87: 0 | Z87: 0 | AA87: invasive | AB87: bird | AC87: 8 | AD87: 0.75 | AE87: soil | AF87: cluster | AG87: Invasive; first shrub to leaf out in spring, last to drop.
A88: Sambucus canadensis | B88: Elderberry | C88: 1 | D88: shrub | E88: woody | F88: 3 | G88: #5a8a3a | H88: #f5f2e2 | I88: #6a6a5a | J88: 95 | K88: 160 | L88: 185 | M88: 225 | N88: 295 | O88: bare | P88: multistem | Q88: 0.75 | R88: 0.35 | S88: 0.8 | T88: 0.2 | U88: 0.2 | V88: 0.3 | W88: 0.65 | X88: 0.3 | Y88: 0 | Z88: 2 | AA88: native | AB88: bird | AC88: 6 | AD88: 0.5 | AE88: soil | AF88: umbel | AG88: Wet drainage notches at the woods edge and ditch.
A89: Alliaria petiolata | B89: Garlic Mustard | C89: 1 | D89: rosette | E89: biennial | F89: 0.8 | G89: #3f7a30 | H89: #f5f5f0 | I89: #3f6a30 | J89: 60 | K89: 100 | L89: 140 | M89: 170 | N89: 190 | O89: rosette | Q89: 0.35 | R89: 0.35 | S89: 0.55 | T89: 0.3 | U89: 0.2 | V89: 0.3 | W89: 0.6 | X89: 0.3 | Y89: 0 | Z89: 0 | AA89: invasive | AB89: gravity | AC89: 10 | AD89: 0.6 | AE89: soil | AF89: spike | AG89: Invades shaded edges; dark green rosettes all winter.
A90: Galium aparine | B90: Cleavers | C90: 1 | D90: mat | E90: winterAnnual | F90: 0.4 | G90: #6f9a46 | H90: #f5f5f0 | I90: #6f9a46 | J90: 300 | K90: 110 | L90: 140 | M90: 160 | N90: 180 | O90: mat | Q90: 0.5 | R90: 0.35 | S90: 0.6 | T90: 0.3 | U90: 0.25 | V90: 0.3 | W90: 0.7 | X90: 0.3 | Y90: 0 | Z90: 0 | AA90: native | AB90: animal | AC90: 6 | AD90: 0.6 | AE90: soil | AF90: plume | AG90: Sticky sprawl in rich, shaded edges in spring.
A91: Impatiens capensis | B91: Jewelweed | C91: 1 | D91: tallForb | E91: summerAnnual | F91: 1.2 | G91: #6a9a4a | H91: #f08a20 | I91: #8a7a5a | J91: 100 | K91: 195 | L91: 270 | M91: 230 | N91: 285 | O91: none | Q91: 0.45 | R91: 0.35 | S91: 0.85 | T91: 0.2 | U91: 0.2 | V91: 0.3 | W91: 0.6 | X91: 0.3 | Y91: 0 | Z91: 2 | AA91: native | AB91: ballistic | AC91: 6 | AD91: 0.5 | AE91: soil | AF91: bell | AG91: Wet, shaded drainage at the woods edge.
A92: Podophyllum peltatum | B92: Mayapple | C92: 1 | D92: forb | E92: perennial | F92: 0.4 | G92: #4f8a3a | H92: #f5f5ef | I92: #6a6040 | J92: 90 | K92: 110 | L92: 125 | M92: 185 | N92: 200 | O92: none | Q92: 0.35 | R92: 0.3 | S92: 0.55 | T92: 0.3 | U92: 0.05 | V92: 0.2 | W92: 0.6 | X92: 0.3 | Y92: 0 | Z92: 3 | AA92: native | AB92: rhizome | AC92: 12 | AD92: 0.55 | AE92: soil | AF92: daisy | AG92: Colonies of umbrellas under the woods edge; gone by midsummer.
A93: Laetiporus sulphureus | B93: Chicken of the Woods | C93: 1 | D93: fungusBracket | E93: fungus | F93: 0.3 | G93: #f0a030 | H93: #f0c040 | I93: #a07040 | J93: 150 | K93: 150 | L93: 280 | M93: 280 | N93: 290 | O93: none | Q93: 0.6 | R93: 0.5 | S93: 0.6 | T93: 0.4 | U93: 0.1 | V93: 0.4 | W93: 0.6 | X93: 0.4 | Y93: 0 | Z93: 0 | AA93: native | AB93: spores | AC93: 4 | AD93: 0.4 | AE93: wood | AF93: cluster | AG93: Bright shelves on dead and dying oak.
A94: Trametes versicolor | B94: Turkey Tail | C94: 1 | D94: fungusBracket | E94: fungus | F94: 0.08 | G94: #8a7a6a | H94: #b8a890 | I94: #7a6a5a | J94: 1 | K94: 1 | L94: 365 | M94: 365 | N94: 999 | O94: evergreen | Q94: 0.6 | R94: 0.5 | S94: 0.6 | T94: 0.4 | U94: 0.1 | V94: 0.4 | W94: 0.6 | X94: 0.4 | Y94: 0 | Z94: 0 | AA94: native | AB94: spores | AC94: 4 | AD94: 0.8 | AE94: wood | AF94: cluster | AG94: Thin banded brackets on fallen logs, all year.
A95: Carex pensylvanica | B95: Pennsylvania Sedge | C95: 1 | D95: sedge | E95: perennial | F95: 0.2 | G95: #6a8a3a | H95: #c8b07a | I95: #a8986a | J95: 60 | K95: 80 | L95: 110 | M95: 140 | N95: 320 | O95: clump | Q95: 0.35 | R95: 0.35 | S95: 0.4 | T95: 0.3 | U95: 0.05 | V95: 0.2 | W95: 0.45 | X95: 0.3 | Y95: 0 | Z95: 5 | AA95: native | AB95: rhizome | AC95: 12 | AD95: 0.6 | AE95: soil | AF95: plume | AG95: Fine sedge lawns under the woods edge.

Sheet Compounds
A1: Code | B1: Class | C1: What it is (in game) | D1: Best Extraction | E1: Destroyed / Degraded By | F1: Gameplay Role | G1: Key Interaction | H1: # Species Carrying | I1: Avg Strength
A2: ALK | B2: Alkaloids | C2: Nitrogen bases; strong bodily effects | D2: Acid-water or alcohol | E2: Heat >80°C | F2: Most potent class; narrowest safety margin | G2: Neutralized by TAN (precipitates) | H2: =COUNTIF(Species!$J$2:$J$186,A2)+COUNTIF(Species!$L$2:$L$186,A2)+COUNTIF(Species!$N$2:$N$186,A2) -> 21 | I2: =IFERROR((SUMIF(Species!$J$2:$J$186,A2,Species!$K$2:$K$186)+SUMIF(Species!$L$2:$L$186,A2,Species!$M$2:$M$186)+SUMIF(Species!$N$2:$N$186,A2,Species!$O$2:$O$186))/H2,0) -> 4.6666667
A3: ANT | B3: Anthocyanins | C3: Red-purple-blue pigments | D3: Water / alcohol | E3: Light, high pH | F3: Color shifts with pH — a built-in indicator | G3: Boosted by ACI (reddens) | H3: =COUNTIF(Species!$J$2:$J$186,A3)+COUNTIF(Species!$L$2:$L$186,A3)+COUNTIF(Species!$N$2:$N$186,A3) -> 10 | I3: =IFERROR((SUMIF(Species!$J$2:$J$186,A3,Species!$K$2:$K$186)+SUMIF(Species!$L$2:$L$186,A3,Species!$M$2:$M$186)+SUMIF(Species!$N$2:$N$186,A3,Species!$O$2:$O$186))/H3,0) -> 3.8
A4: ACI | B4: Organic Acids | C4: Sourness; preservation | D4: Water | E4: Stable | F4: Lowers batch pH; extends shelf life | G4: Pulls ALK into water | H4: =COUNTIF(Species!$J$2:$J$186,A4)+COUNTIF(Species!$L$2:$L$186,A4)+COUNTIF(Species!$N$2:$N$186,A4) -> 16 | I4: =IFERROR((SUMIF(Species!$J$2:$J$186,A4,Species!$K$2:$K$186)+SUMIF(Species!$L$2:$L$186,A4,Species!$M$2:$M$186)+SUMIF(Species!$N$2:$N$186,A4,Species!$O$2:$O$186))/H4,0) -> 3.0625
A5: BIT | B5: Bitters | C5: Bitter principles | D5: Water / alcohol | E5: Stable | F5: Digestive actions; hard to mask | G5: Masked by SUG + VOL | H5: =COUNTIF(Species!$J$2:$J$186,A5)+COUNTIF(Species!$L$2:$L$186,A5)+COUNTIF(Species!$N$2:$N$186,A5) -> 19 | I5: =IFERROR((SUMIF(Species!$J$2:$J$186,A5,Species!$K$2:$K$186)+SUMIF(Species!$L$2:$L$186,A5,Species!$M$2:$M$186)+SUMIF(Species!$N$2:$N$186,A5,Species!$O$2:$O$186))/H5,0) -> 4.6315789
A6: COU | B6: Coumarins | C6: Sweet hay scent; some photo-reactive | D6: Alcohol / oil | E6: UV light | F6: Sun-reaction risk in some species | G6: — | H6: =COUNTIF(Species!$J$2:$J$186,A6)+COUNTIF(Species!$L$2:$L$186,A6)+COUNTIF(Species!$N$2:$N$186,A6) -> 3 | I6: =IFERROR((SUMIF(Species!$J$2:$J$186,A6,Species!$K$2:$K$186)+SUMIF(Species!$L$2:$L$186,A6,Species!$M$2:$M$186)+SUMIF(Species!$N$2:$N$186,A6,Species!$O$2:$O$186))/H6,0) -> 3
A7: FLA | B7: Flavonoids | C7: Broad gentle protective compounds | D7: Alcohol | E7: Slow | F7: Stack well; low risk | G7: Synergy with ACI | H7: =COUNTIF(Species!$J$2:$J$186,A7)+COUNTIF(Species!$L$2:$L$186,A7)+COUNTIF(Species!$N$2:$N$186,A7) -> 28 | I7: =IFERROR((SUMIF(Species!$J$2:$J$186,A7,Species!$K$2:$K$186)+SUMIF(Species!$L$2:$L$186,A7,Species!$M$2:$M$186)+SUMIF(Species!$N$2:$N$186,A7,Species!$O$2:$O$186))/H7,0) -> 2.9285714
A8: GLY | B8: Glycosides | C8: Sugar-bound actives (incl. heart & cyanogenic) | D8: Water | E8: Fermentation, crushing | F8: Hidden potency — released by crushing or time | G8: Released by ferment | H8: =COUNTIF(Species!$J$2:$J$186,A8)+COUNTIF(Species!$L$2:$L$186,A8)+COUNTIF(Species!$N$2:$N$186,A8) -> 24 | I8: =IFERROR((SUMIF(Species!$J$2:$J$186,A8,Species!$K$2:$K$186)+SUMIF(Species!$L$2:$L$186,A8,Species!$M$2:$M$186)+SUMIF(Species!$N$2:$N$186,A8,Species!$O$2:$O$186))/H8,0) -> 3.625
A9: LAT | B9: Latex | C9: Milky sap | D9: Alcohol | E9: Air (gums up) | F9: Handle fresh | G9: — | H9: =COUNTIF(Species!$J$2:$J$186,A9)+COUNTIF(Species!$L$2:$L$186,A9)+COUNTIF(Species!$N$2:$N$186,A9) -> 4 | I9: =IFERROR((SUMIF(Species!$J$2:$J$186,A9,Species!$K$2:$K$186)+SUMIF(Species!$L$2:$L$186,A9,Species!$M$2:$M$186)+SUMIF(Species!$N$2:$N$186,A9,Species!$O$2:$O$186))/H9,0) -> 3.5
A10: MUC | B10: Mucilage | C10: Slime; coats and soothes | D10: Cold water | E10: Heat, alcohol | F10: The game's binder & thickener | G10: Ruined by alcohol | H10: =COUNTIF(Species!$J$2:$J$186,A10)+COUNTIF(Species!$L$2:$L$186,A10)+COUNTIF(Species!$N$2:$N$186,A10) -> 15 | I10: =IFERROR((SUMIF(Species!$J$2:$J$186,A10,Species!$K$2:$K$186)+SUMIF(Species!$L$2:$L$186,A10,Species!$M$2:$M$186)+SUMIF(Species!$N$2:$N$186,A10,Species!$O$2:$O$186))/H10,0) -> 4.2666667
A11: PIG | B11: Pigments | C11: Dye molecules | D11: Water (mordant) | E11: Light | F11: Dye path; mordant choice sets color | G11: Fixed by TAN or alum | H11: =COUNTIF(Species!$J$2:$J$186,A11)+COUNTIF(Species!$L$2:$L$186,A11)+COUNTIF(Species!$N$2:$N$186,A11) -> 14 | I11: =IFERROR((SUMIF(Species!$J$2:$J$186,A11,Species!$K$2:$K$186)+SUMIF(Species!$L$2:$L$186,A11,Species!$M$2:$M$186)+SUMIF(Species!$N$2:$N$186,A11,Species!$O$2:$O$186))/H11,0) -> 3.3571429
A12: RES | B12: Resins | C12: Sticky, waxy, oil-soluble | D12: Oil / high-proof alcohol | E12: Stable | F12: Salves & smokes; slow release | G12: Carried by oils & fats | H12: =COUNTIF(Species!$J$2:$J$186,A12)+COUNTIF(Species!$L$2:$L$186,A12)+COUNTIF(Species!$N$2:$N$186,A12) -> 17 | I12: =IFERROR((SUMIF(Species!$J$2:$J$186,A12,Species!$K$2:$K$186)+SUMIF(Species!$L$2:$L$186,A12,Species!$M$2:$M$186)+SUMIF(Species!$N$2:$N$186,A12,Species!$O$2:$O$186))/H12,0) -> 3.7647059
A13: SAP | B13: Saponins | C13: Foaming, soapy | D13: Water | E13: Stable | F13: Emulsifier; mild toxicity | G13: Lets oil & water mix | H13: =COUNTIF(Species!$J$2:$J$186,A13)+COUNTIF(Species!$L$2:$L$186,A13)+COUNTIF(Species!$N$2:$N$186,A13) -> 18 | I13: =IFERROR((SUMIF(Species!$J$2:$J$186,A13,Species!$K$2:$K$186)+SUMIF(Species!$L$2:$L$186,A13,Species!$M$2:$M$186)+SUMIF(Species!$N$2:$N$186,A13,Species!$O$2:$O$186))/H13,0) -> 3.3888889
... A18: RHZ | B18: Rhizine | C18: Mycelial 'blood' (fictional) | D18: Fresh only | E18: Drying destroys it | F18: Binds living things together | G18: Amplifies SPR | H18: =COUNTIF(Species!$J$2:$J$186,A18)+COUNTIF(Species!$L$2:$L$186,A18)+COUNTIF(Species!$N$2:$N$186,A18) -> 4 | I18: =IFERROR((SUMIF(Species!$J$2:$J$186,A18,Species!$K$2:$K$186)+SUMIF(Species!$L$2:$L$186,A18,Species!$M$2:$M$186)+SUMIF(Species!$N$2:$N$186,A18,Species!$O$2:$O$186))/H18,0) -> 6.5

Sheet Processing
A1: Method | B1: Station | C1: Time | D1: Best Inputs | E1: Strengths | F1: Failure Modes | G1: Player-Controlled Variable
A2: Air Dry | B2: Rack | C2: 2–7 days | D2: Leaf, Flower, Whole | E2: Concentrates; keeps most compounds | F2: VOL loss if hung in sun/heat; mold if humid | G2: Drying room humidity & airflow
A3: Oven Dry | B3: Stone oven | C3: 2 hrs | D3: Root, Bark, Seed | E3: Fast | F3: Destroys VOL & RHZ; scorches above set temp | G3: Dial temperature
A4: Grind | B4: Mortar & pestle | C4: Hand motion | D4: Any dried part | E4: Raises extraction yield; releases GLY | F4: Over-grinding heats & loses VOL | G4: Physical grind count (VR gesture)
A5: Cold Infusion | B5: Jar + water | C5: 12 hrs | D5: MUC plants | E5: Pulls mucilage intact | F5: Weak on everything else | G5: Steep time
A6: Hot Infusion (tea) | B6: Kettle | C6: 5–15 min | D6: Leaf, Flower | E6: Fast water extract | F6: Pulls TAN — over-steep = harsh | G6: Steep time & temp
A7: Decoction | B7: Pot | C7: 20–60 min simmer | D7: Root, Bark, Fruiting body | E7: Extracts tough material | F7: Boils off VOL; kills MUC | G7: Simmer time; reduce volume
A8: Tincture | B8: Spirit jar | C8: 14–28 days | D8: Most | E8: Long shelf life; pulls ALK, RES, FLA | F8: Kills MUC; needs spirit (distilled) | G8: Proof % and macerate days
A9: Acetum | B9: Vinegar jar | C9: 14 days | D9: ALK & mineral plants | E9: Pulls ALK; no alcohol needed | F9: Weaker than tincture | G9: Vinegar made in-house from ferments
A10: Infused Oil | B10: Oil jar / double boiler | C10: 2–6 weeks or 4 hrs warm | D10: RES, VOL plants | E10: Salve base | F10: Rancid if water present (fresh herb) | G10: Dryness of input
A11: Salve | B11: Double boiler + beeswax | C11: 30 min | D11: Infused oil | E11: Shelf-stable topical | F11: Wax ratio sets hardness | G11: Oil:wax ratio
A12: Syrup | B12: Pot + honey/sugar | C12: 20 min | D12: Decoctions, fruit | E12: Masks bitterness; preserves | F12: Ferments if under-sugared | G12: Sugar ratio
... A18: Graft | B18: Living altar | C18: 1 season | D18: Garden plants + Graftwort | E18: Hybrid species with merged compounds | F18: Rejection kills both | G18: Compatibility score

Sheet Seasonal Calendar
A1: Species | B1: Part | C1: Jan | D1: Feb | E1: Mar | F1: Apr | G1: May | H1: Jun | I1: Jul | J1: Aug | K1: Sep | L1: Oct | M1: Nov | N1: Dec
A2: =Species!B2 -> Lamb's Quarters | B2: =Species!F2 -> Leaf | C2: =IF(Species!$G2<=Species!$H2,IF(AND(1>=Species!$G2,1<=Species!$H2),"H",""),IF(OR(1>=Species!$G2,1<=Species!$H2),"H",""))&IF(Species!$I2=1,"S","") | D2: =IF(Species!$G2<=Species!$H2,IF(AND(2>=Species!$G2,2<=Species!$H2),"H",""),IF(OR(2>=Species!$G2,2<=Species!$H2),"H",""))&IF(Species!$I2=2,"S","") | E2: =IF(Species!$G2<=Species!$H2,IF(AND(3>=Species!$G2,3<=Species!$H2),"H",""),IF(OR(3>=Species!$G2,3<=Species!$H2),"H",""))&IF(Species!$I2=3,"S","") | F2: =IF(Species!$G2<=Species!$H2,IF(AND(4>=Species!$G2,4<=Species!$H2),"H",""),IF(OR(4>=Species!$G2,4<=Species!$H2),"H",""))&IF(Species!$I2=4,"S","") | G2: =IF(Species!$G2<=Species!$H2,IF(AND(5>=Species!$G2,5<=Species!$H2),"H",""),IF(OR(5>=Species!$G2,5<=Species!$H2),"H",""))&IF(Species!$I2=5,"S","") -> H | H2: =IF(Species!$G2<=Species!$H2,IF(AND(6>=Species!$G2,6<=Species!$H2),"H",""),IF(OR(6>=Species!$G2,6<=Species!$H2),"H",""))&IF(Species!$I2=6,"S","") -> H | I2: =IF(Species!$G2<=Species!$H2,IF(AND(7>=Species!$G2,7<=Species!$H2),"H",""),IF(OR(7>=Species!$G2,7<=Species!$H2),"H",""))&IF(Species!$I2=7,"S","") -> H | J2: =IF(Species!$G2<=Species!$H2,IF(AND(8>=Species!$G2,8<=Species!$H2),"H",""),IF(OR(8>=Species!$G2,8<=Species!$H2),"H",""))&IF(Species!$I2=8,"S","") -> H | K2: =IF(Species!$G2<=Species!$H2,IF(AND(9>=Species!$G2,9<=Species!$H2),"H",""),IF(OR(9>=Species!$G2,9<=Species!$H2),"H",""))&IF(Species!$I2=9,"S","") -> S | L2: =IF(Species!$G2<=Species!$H2,IF(AND(10>=Species!$G2,10<=Species!$H2),"H",""),IF(OR(10>=Species!$G2,10<=Species!$H2),"H",""))&IF(Species!$I2=10,"S","") | M2: =IF(Species!$G2<=Species!$H2,IF(AND(11>=Species!$G2,11<=Species!$H2),"H",""),IF(OR(11>=Species!$G2,11<=Species!$H2),"H",""))&IF(Species!$I2=11,"S","") | N2: =IF(Species!$G2<=Species!$H2,IF(AND(12>=Species!$G2,12<=Species!$H2),"H",""),IF(OR(12>=Species!$G2,12<=Species!$H2),"H",""))&IF(Species!$I2=12,"S","")
A3: =Species!B3 -> Chickweed | B3: =Species!F3 -> Whole | C3: =IF(Species!$G3<=Species!$H3,IF(AND(1>=Species!$G3,1<=Species!$H3),"H",""),IF(OR(1>=Species!$G3,1<=Species!$H3),"H",""))&IF(Species!$I3=1,"S","") | D3: =IF(Species!$G3<=Species!$H3,IF(AND(2>=Species!$G3,2<=Species!$H3),"H",""),IF(OR(2>=Species!$G3,2<=Species!$H3),"H",""))&IF(Species!$I3=2,"S","") | E3: =IF(Species!$G3<=Species!$H3,IF(AND(3>=Species!$G3,3<=Species!$H3),"H",""),IF(OR(3>=Species!$G3,3<=Species!$H3),"H",""))&IF(Species!$I3=3,"S","") -> H | F3: =IF(Species!$G3<=Species!$H3,IF(AND(4>=Species!$G3,4<=Species!$H3),"H",""),IF(OR(4>=Species!$G3,4<=Species!$H3),"H",""))&IF(Species!$I3=4,"S","") -> H | G3: =IF(Species!$G3<=Species!$H3,IF(AND(5>=Species!$G3,5<=Species!$H3),"H",""),IF(OR(5>=Species!$G3,5<=Species!$H3),"H",""))&IF(Species!$I3=5,"S","") -> HS | H3: =IF(Species!$G3<=Species!$H3,IF(AND(6>=Species!$G3,6<=Species!$H3),"H",""),IF(OR(6>=Species!$G3,6<=Species!$H3),"H",""))&IF(Species!$I3=6,"S","") | I3: =IF(Species!$G3<=Species!$H3,IF(AND(7>=Species!$G3,7<=Species!$H3),"H",""),IF(OR(7>=Species!$G3,7<=Species!$H3),"H",""))&IF(Species!$I3=7,"S","") | J3: =IF(Species!$G3<=Species!$H3,IF(AND(8>=Species!$G3,8<=Species!$H3),"H",""),IF(OR(8>=Species!$G3,8<=Species!$H3),"H",""))&IF(Species!$I3=8,"S","") | K3: =IF(Species!$G3<=Species!$H3,IF(AND(9>=Species!$G3,9<=Species!$H3),"H",""),IF(OR(9>=Species!$G3,9<=Species!$H3),"H",""))&IF(Species!$I3=9,"S","") | L3: =IF(Species!$G3<=Species!$H3,IF(AND(10>=Species!$G3,10<=Species!$H3),"H",""),IF(OR(10>=Species!$G3,10<=Species!$H3),"H",""))&IF(Species!$I3=10,"S","") | M3: =IF(Species!$G3<=Species!$H3,IF(AND(11>=Species!$G3,11<=Species!$H3),"H",""),IF(OR(11>=Species!$G3,11<=Species!$H3),"H",""))&IF(Species!$I3=11,"S","") | N3: =IF(Species!$G3<=Species!$H3,IF(AND(12>=Species!$G3,12<=Species!$H3),"H",""),IF(OR(12>=Species!$G3,12<=Species!$H3),"H",""))&IF(Species!$I3=12,"S","")
A4: =Species!B4 -> Purple Deadnettle | B4: =Species!F4 -> Whole | C4: =IF(Species!$G4<=Species!$H4,IF(AND(1>=Species!$G4,1<=Species!$H4),"H",""),IF(OR(1>=Species!$G4,1<=Species!$H4),"H",""))&IF(Species!$I4=1,"S","") | D4: =IF(Species!$G4<=Species!$H4,IF(AND(2>=Species!$G4,2<=Species!$H4),"H",""),IF(OR(2>=Species!$G4,2<=Species!$H4),"H",""))&IF(Species!$I4=2,"S","") | E4: =IF(Species!$G4<=Species!$H4,IF(AND(3>=Species!$G4,3<=Species!$H4),"H",""),IF(OR(3>=Species!$G4,3<=Species!$H4),"H",""))&IF(Species!$I4=3,"S","") -> H | F4: =IF(Species!$G4<=Species!$H4,IF(AND(4>=Species!$G4,4<=Species!$H4),"H",""),IF(OR(4>=Species!$G4,4<=Species!$H4),"H",""))&IF(Species!$I4=4,"S","") -> H | G4: =IF(Species!$G4<=Species!$H4,IF(AND(5>=Species!$G4,5<=Species!$H4),"H",""),IF(OR(5>=Species!$G4,5<=Species!$H4),"H",""))&IF(Species!$I4=5,"S","") -> HS | H4: =IF(Species!$G4<=Species!$H4,IF(AND(6>=Species!$G4,6<=Species!$H4),"H",""),IF(OR(6>=Species!$G4,6<=Species!$H4),"H",""))&IF(Species!$I4=6,"S","") | I4: =IF(Species!$G4<=Species!$H4,IF(AND(7>=Species!$G4,7<=Species!$H4),"H",""),IF(OR(7>=Species!$G4,7<=Species!$H4),"H",""))&IF(Species!$I4=7,"S","") | J4: =IF(Species!$G4<=Species!$H4,IF(AND(8>=Species!$G4,8<=Species!$H4),"H",""),IF(OR(8>=Species!$G4,8<=Species!$H4),"H",""))&IF(Species!$I4=8,"S","") | K4: =IF(Species!$G4<=Species!$H4,IF(AND(9>=Species!$G4,9<=Species!$H4),"H",""),IF(OR(9>=Species!$G4,9<=Species!$H4),"H",""))&IF(Species!$I4=9,"S","") | L4: =IF(Species!$G4<=Species!$H4,IF(AND(10>=Species!$G4,10<=Species!$H4),"H",""),IF(OR(10>=Species!$G4,10<=Species!$H4),"H",""))&IF(Species!$I4=10,"S","") | M4: =IF(Species!$G4<=Species!$H4,IF(AND(11>=Species!$G4,11<=Species!$H4),"H",""),IF(OR(11>=Species!$G4,11<=Species!$H4),"H",""))&IF(Species!$I4=11,"S","") | N4: =IF(Species!$G4<=Species!$H4,IF(AND(12>=Species!$G4,12<=Species!$H4),"H",""),IF(OR(12>=Species!$G4,12<=Species!$H4),"H",""))&IF(Species!$I4=12,"S","")
A5: =Species!B5 -> Henbit | B5: =Species!F5 -> Whole | C5: =IF(Species!$G5<=Species!$H5,IF(AND(1>=Species!$G5,1<=Species!$H5),"H",""),IF(OR(1>=Species!$G5,1<=Species!$H5),"H",""))&IF(Species!$I5=1,"S","") | D5: =IF(Species!$G5<=Species!$H5,IF(AND(2>=Species!$G5,2<=Species!$H5),"H",""),IF(OR(2>=Species!$G5,2<=Species!$H5),"H",""))&IF(Species!$I5=2,"S","") | E5: =IF(Species!$G5<=Species!$H5,IF(AND(3>=Species!$G5,3<=Species!$H5),"H",""),IF(OR(3>=Species!$G5,3<=Species!$H5),"H",""))&IF(Species!$I5=3,"S","") -> H | F5: =IF(Species!$G5<=Species!$H5,IF(AND(4>=Species!$G5,4<=Species!$H5),"H",""),IF(OR(4>=Species!$G5,4<=Species!$H5),"H",""))&IF(Species!$I5=4,"S","") -> H | G5: =IF(Species!$G5<=Species!$H5,IF(AND(5>=Species!$G5,5<=Species!$H5),"H",""),IF(OR(5>=Species!$G5,5<=Species!$H5),"H",""))&IF(Species!$I5=5,"S","") -> HS | H5: =IF(Species!$G5<=Species!$H5,IF(AND(6>=Species!$G5,6<=Species!$H5),"H",""),IF(OR(6>=Species!$G5,6<=Species!$H5),"H",""))&IF(Species!$I5=6,"S","") | I5: =IF(Species!$G5<=Species!$H5,IF(AND(7>=Species!$G5,7<=Species!$H5),"H",""),IF(OR(7>=Species!$G5,7<=Species!$H5),"H",""))&IF(Species!$I5=7,"S","") | J5: =IF(Species!$G5<=Species!$H5,IF(AND(8>=Species!$G5,8<=Species!$H5),"H",""),IF(OR(8>=Species!$G5,8<=Species!$H5),"H",""))&IF(Species!$I5=8,"S","") | K5: =IF(Species!$G5<=Species!$H5,IF(AND(9>=Species!$G5,9<=Species!$H5),"H",""),IF(OR(9>=Species!$G5,9<=Species!$H5),"H",""))&IF(Species!$I5=9,"S","") | L5: =IF(Species!$G5<=Species!$H5,IF(AND(10>=Species!$G5,10<=Species!$H5),"H",""),IF(OR(10>=Species!$G5,10<=Species!$H5),"H",""))&IF(Species!$I5=10,"S","") | M5: =IF(Species!$G5<=Species!$H5,IF(AND(11>=Species!$G5,11<=Species!$H5),"H",""),IF(OR(11>=Species!$G5,11<=Species!$H5),"H",""))&IF(Species!$I5=11,"S","") | N5: =IF(Species!$G5<=Species!$H5,IF(AND(12>=Species!$G5,12<=Species!$H5),"H",""),IF(OR(12>=Species!$G5,12<=Species!$H5),"H",""))&IF(Species!$I5=12,"S","")
A6: =Species!B6 -> Dandelion | B6: =Species!F6 -> Root | C6: =IF(Species!$G6<=Species!$H6,IF(AND(1>=Species!$G6,1<=Species!$H6),"H",""),IF(OR(1>=Species!$G6,1<=Species!$H6),"H",""))&IF(Species!$I6=1,"S","") | D6: =IF(Species!$G6<=Species!$H6,IF(AND(2>=Species!$G6,2<=Species!$H6),"H",""),IF(OR(2>=Species!$G6,2<=Species!$H6),"H",""))&IF(Species!$I6=2,"S","") | E6: =IF(Species!$G6<=Species!$H6,IF(AND(3>=Species!$G6,3<=Species!$H6),"H",""),IF(OR(3>=Species!$G6,3<=Species!$H6),"H",""))&IF(Species!$I6=3,"S","") -> H | F6: =IF(Species!$G6<=Species!$H6,IF(AND(4>=Species!$G6,4<=Species!$H6),"H",""),IF(OR(4>=Species!$G6,4<=Species!$H6),"H",""))&IF(Species!$I6=4,"S","") -> H | G6: =IF(Species!$G6<=Species!$H6,IF(AND(5>=Species!$G6,5<=Species!$H6),"H",""),IF(OR(5>=Species!$G6,5<=Species!$H6),"H",""))&IF(Species!$I6=5,"S","") -> HS | H6: =IF(Species!$G6<=Species!$H6,IF(AND(6>=Species!$G6,6<=Species!$H6),"H",""),IF(OR(6>=Species!$G6,6<=Species!$H6),"H",""))&IF(Species!$I6=6,"S","") -> H | I6: =IF(Species!$G6<=Species!$H6,IF(AND(7>=Species!$G6,7<=Species!$H6),"H",""),IF(OR(7>=Species!$G6,7<=Species!$H6),"H",""))&IF(Species!$I6=7,"S","") -> H | J6: =IF(Species!$G6<=Species!$H6,IF(AND(8>=Species!$G6,8<=Species!$H6),"H",""),IF(OR(8>=Species!$G6,8<=Species!$H6),"H",""))&IF(Species!$I6=8,"S","") -> H | K6: =IF(Species!$G6<=Species!$H6,IF(AND(9>=Species!$G6,9<=Species!$H6),"H",""),IF(OR(9>=Species!$G6,9<=Species!$H6),"H",""))&IF(Species!$I6=9,"S","") -> H | L6: =IF(Species!$G6<=Species!$H6,IF(AND(10>=Species!$G6,10<=Species!$H6),"H",""),IF(OR(10>=Species!$G6,10<=Species!$H6),"H",""))&IF(Species!$I6=10,"S","") -> H | M6: =IF(Species!$G6<=Species!$H6,IF(AND(11>=Species!$G6,11<=Species!$H6),"H",""),IF(OR(11>=Species!$G6,11<=Species!$H6),"H",""))&IF(Species!$I6=11,"S","") -> H | N6: =IF(Species!$G6<=Species!$H6,IF(AND(12>=Species!$G6,12<=Species!$H6),"H",""),IF(OR(12>=Species!$G6,12<=Species!$H6),"H",""))&IF(Species!$I6=12,"S","")
A7: =Species!B7 -> Common Blue Violet | B7: =Species!F7 -> Leaf | C7: =IF(Species!$G7<=Species!$H7,IF(AND(1>=Species!$G7,1<=Species!$H7),"H",""),IF(OR(1>=Species!$G7,1<=Species!$H7),"H",""))&IF(Species!$I7=1,"S","") | D7: =IF(Species!$G7<=Species!$H7,IF(AND(2>=Species!$G7,2<=Species!$H7),"H",""),IF(OR(2>=Species!$G7,2<=Species!$H7),"H",""))&IF(Species!$I7=2,"S","") | E7: =IF(Species!$G7<=Species!$H7,IF(AND(3>=Species!$G7,3<=Species!$H7),"H",""),IF(OR(3>=Species!$G7,3<=Species!$H7),"H",""))&IF(Species!$I7=3,"S","") -> H | F7: =IF(Species!$G7<=Species!$H7,IF(AND(4>=Species!$G7,4<=Species!$H7),"H",""),IF(OR(4>=Species!$G7,4<=Species!$H7),"H",""))&IF(Species!$I7=4,"S","") -> H | G7: =IF(Species!$G7<=Species!$H7,IF(AND(5>=Species!$G7,5<=Species!$H7),"H",""),IF(OR(5>=Species!$G7,5<=Species!$H7),"H",""))&IF(Species!$I7=5,"S","") -> H | H7: =IF(Species!$G7<=Species!$H7,IF(AND(6>=Species!$G7,6<=Species!$H7),"H",""),IF(OR(6>=Species!$G7,6<=Species!$H7),"H",""))&IF(Species!$I7=6,"S","") -> HS | I7: =IF(Species!$G7<=Species!$H7,IF(AND(7>=Species!$G7,7<=Species!$H7),"H",""),IF(OR(7>=Species!$G7,7<=Species!$H7),"H",""))&IF(Species!$I7=7,"S","") | J7: =IF(Species!$G7<=Species!$H7,IF(AND(8>=Species!$G7,8<=Species!$H7),"H",""),IF(OR(8>=Species!$G7,8<=Species!$H7),"H",""))&IF(Species!$I7=8,"S","") | K7: =IF(Species!$G7<=Species!$H7,IF(AND(9>=Species!$G7,9<=Species!$H7),"H",""),IF(OR(9>=Species!$G7,9<=Species!$H7),"H",""))&IF(Species!$I7=9,"S","") | L7: =IF(Species!$G7<=Species!$H7,IF(AND(10>=Species!$G7,10<=Species!$H7),"H",""),IF(OR(10>=Species!$G7,10<=Species!$H7),"H",""))&IF(Species!$I7=10,"S","") | M7: =IF(Species!$G7<=Species!$H7,IF(AND(11>=Species!$G7,11<=Species!$H7),"H",""),IF(OR(11>=Species!$G7,11<=Species!$H7),"H",""))&IF(Species!$I7=11,"S","") | N7: =IF(Species!$G7<=Species!$H7,IF(AND(12>=Species!$G7,12<=Species!$H7),"H",""),IF(OR(12>=Species!$G7,12<=Species!$H7),"H",""))&IF(Species!$I7=12,"S","")
A8: =Species!B8 -> Cleavers | B8: =Species!F8 -> Whole | C8: =IF(Species!$G8<=Species!$H8,IF(AND(1>=Species!$G8,1<=Species!$H8),"H",""),IF(OR(1>=Species!$G8,1<=Species!$H8),"H",""))&IF(Species!$I8=1,"S","") | D8: =IF(Species!$G8<=Species!$H8,IF(AND(2>=Species!$G8,2<=Species!$H8),"H",""),IF(OR(2>=Species!$G8,2<=Species!$H8),"H",""))&IF(Species!$I8=2,"S","") | E8: =IF(Species!$G8<=Species!$H8,IF(AND(3>=Species!$G8,3<=Species!$H8),"H",""),IF(OR(3>=Species!$G8,3<=Species!$H8),"H",""))&IF(Species!$I8=3,"S","") | F8: =IF(Species!$G8<=Species!$H8,IF(AND(4>=Species!$G8,4<=Species!$H8),"H",""),IF(OR(4>=Species!$G8,4<=Species!$H8),"H",""))&IF(Species!$I8=4,"S","") -> H | G8: =IF(Species!$G8<=Species!$H8,IF(AND(5>=Species!$G8,5<=Species!$H8),"H",""),IF(OR(5>=Species!$G8,5<=Species!$H8),"H",""))&IF(Species!$I8=5,"S","") -> H | H8: =IF(Species!$G8<=Species!$H8,IF(AND(6>=Species!$G8,6<=Species!$H8),"H",""),IF(OR(6>=Species!$G8,6<=Species!$H8),"H",""))&IF(Species!$I8=6,"S","") -> HS | I8: =IF(Species!$G8<=Species!$H8,IF(AND(7>=Species!$G8,7<=Species!$H8),"H",""),IF(OR(7>=Species!$G8,7<=Species!$H8),"H",""))&IF(Species!$I8=7,"S","") | J8: =IF(Species!$G8<=Species!$H8,IF(AND(8>=Species!$G8,8<=Species!$H8),"H",""),IF(OR(8>=Species!$G8,8<=Species!$H8),"H",""))&IF(Species!$I8=8,"S","") | K8: =IF(Species!$G8<=Species!$H8,IF(AND(9>=Species!$G8,9<=Species!$H8),"H",""),IF(OR(9>=Species!$G8,9<=Species!$H8),"H",""))&IF(Species!$I8=9,"S","") | L8: =IF(Species!$G8<=Species!$H8,IF(AND(10>=Species!$G8,10<=Species!$H8),"H",""),IF(OR(10>=Species!$G8,10<=Species!$H8),"H",""))&IF(Species!$I8=10,"S","") | M8: =IF(Species!$G8<=Species!$H8,IF(AND(11>=Species!$G8,11<=Species!$H8),"H",""),IF(OR(11>=Species!$G8,11<=Species!$H8),"H",""))&IF(Species!$I8=11,"S","") | N8: =IF(Species!$G8<=Species!$H8,IF(AND(12>=Species!$G8,12<=Species!$H8),"H",""),IF(OR(12>=Species!$G8,12<=Species!$H8),"H",""))&IF(Species!$I8=12,"S","")
A9: =Species!B9 -> Wood Sorrel | B9: =Species!F9 -> Leaf | C9: =IF(Species!$G9<=Species!$H9,IF(AND(1>=Species!$G9,1<=Species!$H9),"H",""),IF(OR(1>=Species!$G9,1<=Species!$H9),"H",""))&IF(Species!$I9=1,"S","") | D9: =IF(Species!$G9<=Species!$H9,IF(AND(2>=Species!$G9,2<=Species!$H9),"H",""),IF(OR(2>=Species!$G9,2<=Species!$H9),"H",""))&IF(Species!$I9=2,"S","") | E9: =IF(Species!$G9<=Species!$H9,IF(AND(3>=Species!$G9,3<=Species!$H9),"H",""),IF(OR(3>=Species!$G9,3<=Species!$H9),"H",""))&IF(Species!$I9=3,"S","") | F9: =IF(Species!$G9<=Species!$H9,IF(AND(4>=Species!$G9,4<=Species!$H9),"H",""),IF(OR(4>=Species!$G9,4<=Species!$H9),"H",""))&IF(Species!$I9=4,"S","") | G9: =IF(Species!$G9<=Species!$H9,IF(AND(5>=Species!$G9,5<=Species!$H9),"H",""),IF(OR(5>=Species!$G9,5<=Species!$H9),"H",""))&IF(Species!$I9=5,"S","") -> H | H9: =IF(Species!$G9<=Species!$H9,IF(AND(6>=Species!$G9,6<=Species!$H9),"H",""),IF(OR(6>=Species!$G9,6<=Species!$H9),"H",""))&IF(Species!$I9=6,"S","") -> H | I9: =IF(Species!$G9<=Species!$H9,IF(AND(7>=Species!$G9,7<=Species!$H9),"H",""),IF(OR(7>=Species!$G9,7<=Species!$H9),"H",""))&IF(Species!$I9=7,"S","") -> HS | J9: =IF(Species!$G9<=Species!$H9,IF(AND(8>=Species!$G9,8<=Species!$H9),"H",""),IF(OR(8>=Species!$G9,8<=Species!$H9),"H",""))&IF(Species!$I9=8,"S","") -> H | K9: =IF(Species!$G9<=Species!$H9,IF(AND(9>=Species!$G9,9<=Species!$H9),"H",""),IF(OR(9>=Species!$G9,9<=Species!$H9),"H",""))&IF(Species!$I9=9,"S","") -> H | L9: =IF(Species!$G9<=Species!$H9,IF(AND(10>=Species!$G9,10<=Species!$H9),"H",""),IF(OR(10>=Species!$G9,10<=Species!$H9),"H",""))&IF(Species!$I9=10,"S","") -> H | M9: =IF(Species!$G9<=Species!$H9,IF(AND(11>=Species!$G9,11<=Species!$H9),"H",""),IF(OR(11>=Species!$G9,11<=Species!$H9),"H",""))&IF(Species!$I9=11,"S","") | N9: =IF(Species!$G9<=Species!$H9,IF(AND(12>=Species!$G9,12<=Species!$H9),"H",""),IF(OR(12>=Species!$G9,12<=Species!$H9),"H",""))&IF(Species!$I9=12,"S","")
A10: =Species!B10 -> Sheep Sorrel | B10: =Species!F10 -> Leaf | C10: =IF(Species!$G10<=Species!$H10,IF(AND(1>=Species!$G10,1<=Species!$H10),"H",""),IF(OR(1>=Species!$G10,1<=Species!$H10),"H",""))&IF(Species!$I10=1,"S","") | D10: =IF(Species!$G10<=Species!$H10,IF(AND(2>=Species!$G10,2<=Species!$H10),"H",""),IF(OR(2>=Species!$G10,2<=Species!$H10),"H",""))&IF(Species!$I10=2,"S","") | E10: =IF(Species!$G10<=Species!$H10,IF(AND(3>=Species!$G10,3<=Species!$H10),"H",""),IF(OR(3>=Species!$G10,3<=Species!$H10),"H",""))&IF(Species!$I10=3,"S","") | F10: =IF(Species!$G10<=Species!$H10,IF(AND(4>=Species!$G10,4<=Species!$H10),"H",""),IF(OR(4>=Species!$G10,4<=Species!$H10),"H",""))&IF(Species!$I10=4,"S","") -> H | G10: =IF(Species!$G10<=Species!$H10,IF(AND(5>=Species!$G10,5<=Species!$H10),"H",""),IF(OR(5>=Species!$G10,5<=Species!$H10),"H",""))&IF(Species!$I10=5,"S","") -> H | H10: =IF(Species!$G10<=Species!$H10,IF(AND(6>=Species!$G10,6<=Species!$H10),"H",""),IF(OR(6>=Species!$G10,6<=Species!$H10),"H",""))&IF(Species!$I10=6,"S","") -> H | I10: =IF(Species!$G10<=Species!$H10,IF(AND(7>=Species!$G10,7<=Species!$H10),"H",""),IF(OR(7>=Species!$G10,7<=Species!$H10),"H",""))&IF(Species!$I10=7,"S","") -> HS | J10: =IF(Species!$G10<=Species!$H10,IF(AND(8>=Species!$G10,8<=Species!$H10),"H",""),IF(OR(8>=Species!$G10,8<=Species!$H10),"H",""))&IF(Species!$I10=8,"S","") | K10: =IF(Species!$G10<=Species!$H10,IF(AND(9>=Species!$G10,9<=Species!$H10),"H",""),IF(OR(9>=Species!$G10,9<=Species!$H10),"H",""))&IF(Species!$I10=9,"S","") | L10: =IF(Species!$G10<=Species!$H10,IF(AND(10>=Species!$G10,10<=Species!$H10),"H",""),IF(OR(10>=Species!$G10,10<=Species!$H10),"H",""))&IF(Species!$I10=10,"S","") | M10: =IF(Species!$G10<=Species!$H10,IF(AND(11>=Species!$G10,11<=Species!$H10),"H",""),IF(OR(11>=Species!$G10,11<=Species!$H10),"H",""))&IF(Species!$I10=11,"S","") | N10: =IF(Species!$G10<=Species!$H10,IF(AND(12>=Species!$G10,12<=Species!$H10),"H",""),IF(OR(12>=Species!$G10,12<=Species!$H10),"H",""))&IF(Species!$I10=12,"S","")
A11: =Species!B11 -> Curly Dock | B11: =Species!F11 -> Root | C11: =IF(Species!$G11<=Species!$H11,IF(AND(1>=Species!$G11,1<=Species!$H11),"H",""),IF(OR(1>=Species!$G11,1<=Species!$H11),"H",""))&IF(Species!$I11=1,"S","") | D11: =IF(Species!$G11<=Species!$H11,IF(AND(2>=Species!$G11,2<=Species!$H11),"H",""),IF(OR(2>=Species!$G11,2<=Species!$H11),"H",""))&IF(Species!$I11=2,"S","") | E11: =IF(Species!$G11<=Species!$H11,IF(AND(3>=Species!$G11,3<=Species!$H11),"H",""),IF(OR(3>=Species!$G11,3<=Species!$H11),"H",""))&IF(Species!$I11=3,"S","") | F11: =IF(Species!$G11<=Species!$H11,IF(AND(4>=Species!$G11,4<=Species!$H11),"H",""),IF(OR(4>=Species!$G11,4<=Species!$H11),"H",""))&IF(Species!$I11=4,"S","") | G11: =IF(Species!$G11<=Species!$H11,IF(AND(5>=Species!$G11,5<=Species!$H11),"H",""),IF(OR(5>=Species!$G11,5<=Species!$H11),"H",""))&IF(Species!$I11=5,"S","") | H11: =IF(Species!$G11<=Species!$H11,IF(AND(6>=Species!$G11,6<=Species!$H11),"H",""),IF(OR(6>=Species!$G11,6<=Species!$H11),"H",""))&IF(Species!$I11=6,"S","") | I11: =IF(Species!$G11<=Species!$H11,IF(AND(7>=Species!$G11,7<=Species!$H11),"H",""),IF(OR(7>=Species!$G11,7<=Species!$H11),"H",""))&IF(Species!$I11=7,"S","") | J11: =IF(Species!$G11<=Species!$H11,IF(AND(8>=Species!$G11,8<=Species!$H11),"H",""),IF(OR(8>=Species!$G11,8<=Species!$H11),"H",""))&IF(Species!$I11=8,"S","") -> S | K11: =IF(Species!$G11<=Species!$H11,IF(AND(9>=Species!$G11,9<=Species!$H11),"H",""),IF(OR(9>=Species!$G11,9<=Species!$H11),"H",""))&IF(Species!$I11=9,"S","") -> H | L11: =IF(Species!$G11<=Species!$H11,IF(AND(10>=Species!$G11,10<=Species!$H11),"H",""),IF(OR(10>=Species!$G11,10<=Species!$H11),"H",""))&IF(Species!$I11=10,"S","") -> H | M11: =IF(Species!$G11<=Species!$H11,IF(AND(11>=Species!$G11,11<=Species!$H11),"H",""),IF(OR(11>=Species!$G11,11<=Species!$H11),"H",""))&IF(Species!$I11=11,"S","") -> H | N11: =IF(Species!$G11<=Species!$H11,IF(AND(12>=Species!$G11,12<=Species!$H11),"H",""),IF(OR(12>=Species!$G11,12<=Species!$H11),"H",""))&IF(Species!$I11=12,"S","")
A12: =Species!B12 -> Red Clover | B12: =Species!F12 -> Flower | C12: =IF(Species!$G12<=Species!$H12,IF(AND(1>=Species!$G12,1<=Species!$H12),"H",""),IF(OR(1>=Species!$G12,1<=Species!$H12),"H",""))&IF(Species!$I12=1,"S","") | D12: =IF(Species!$G12<=Species!$H12,IF(AND(2>=Species!$G12,2<=Species!$H12),"H",""),IF(OR(2>=Species!$G12,2<=Species!$H12),"H",""))&IF(Species!$I12=2,"S","") | E12: =IF(Species!$G12<=Species!$H12,IF(AND(3>=Species!$G12,3<=Species!$H12),"H",""),IF(OR(3>=Species!$G12,3<=Species!$H12),"H",""))&IF(Species!$I12=3,"S","") | F12: =IF(Species!$G12<=Species!$H12,IF(AND(4>=Species!$G12,4<=Species!$H12),"H",""),IF(OR(4>=Species!$G12,4<=Species!$H12),"H",""))&IF(Species!$I12=4,"S","") | G12: =IF(Species!$G12<=Species!$H12,IF(AND(5>=Species!$G12,5<=Species!$H12),"H",""),IF(OR(5>=Species!$G12,5<=Species!$H12),"H",""))&IF(Species!$I12=5,"S","") -> H | H12: =IF(Species!$G12<=Species!$H12,IF(AND(6>=Species!$G12,6<=Species!$H12),"H",""),IF(OR(6>=Species!$G12,6<=Species!$H12),"H",""))&IF(Species!$I12=6,"S","") -> H | I12: =IF(Species!$G12<=Species!$H12,IF(AND(7>=Species!$G12,7<=Species!$H12),"H",""),IF(OR(7>=Species!$G12,7<=Species!$H12),"H",""))&IF(Species!$I12=7,"S","") -> H | J12: =IF(Species!$G12<=Species!$H12,IF(AND(8>=Species!$G12,8<=Species!$H12),"H",""),IF(OR(8>=Species!$G12,8<=Species!$H12),"H",""))&IF(Species!$I12=8,"S","") -> HS | K12: =IF(Species!$G12<=Species!$H12,IF(AND(9>=Species!$G12,9<=Species!$H12),"H",""),IF(OR(9>=Species!$G12,9<=Species!$H12),"H",""))&IF(Species!$I12=9,"S","") | L12: =IF(Species!$G12<=Species!$H12,IF(AND(10>=Species!$G12,10<=Species!$H12),"H",""),IF(OR(10>=Species!$G12,10<=Species!$H12),"H",""))&IF(Species!$I12=10,"S","") | M12: =IF(Species!$G12<=Species!$H12,IF(AND(11>=Species!$G12,11<=Species!$H12),"H",""),IF(OR(11>=Species!$G12,11<=Species!$H12),"H",""))&IF(Species!$I12=11,"S","") | N12: =IF(Species!$G12<=Species!$H12,IF(AND(12>=Species!$G12,12<=Species!$H12),"H",""),IF(OR(12>=Species!$G12,12<=Species!$H12),"H",""))&IF(Species!$I12=12,"S","")
A13: =Species!B13 -> White Clover | B13: =Species!F13 -> Flower | C13: =IF(Species!$G13<=Species!$H13,IF(AND(1>=Species!$G13,1<=Species!$H13),"H",""),IF(OR(1>=Species!$G13,1<=Species!$H13),"H",""))&IF(Species!$I13=1,"S","") | D13: =IF(Species!$G13<=Species!$H13,IF(AND(2>=Species!$G13,2<=Species!$H13),"H",""),IF(OR(2>=Species!$G13,2<=Species!$H13),"H",""))&IF(Species!$I13=2,"S","") | E13: =IF(Species!$G13<=Species!$H13,IF(AND(3>=Species!$G13,3<=Species!$H13),"H",""),IF(OR(3>=Species!$G13,3<=Species!$H13),"H",""))&IF(Species!$I13=3,"S","") | F13: =IF(Species!$G13<=Species!$H13,IF(AND(4>=Species!$G13,4<=Species!$H13),"H",""),IF(OR(4>=Species!$G13,4<=Species!$H13),"H",""))&IF(Species!$I13=4,"S","") | G13: =IF(Species!$G13<=Species!$H13,IF(AND(5>=Species!$G13,5<=Species!$H13),"H",""),IF(OR(5>=Species!$G13,5<=Species!$H13),"H",""))&IF(Species!$I13=5,"S","") -> H | H13: =IF(Species!$G13<=Species!$H13,IF(AND(6>=Species!$G13,6<=Species!$H13),"H",""),IF(OR(6>=Species!$G13,6<=Species!$H13),"H",""))&IF(Species!$I13=6,"S","") -> H | I13: =IF(Species!$G13<=Species!$H13,IF(AND(7>=Species!$G13,7<=Species!$H13),"H",""),IF(OR(7>=Species!$G13,7<=Species!$H13),"H",""))&IF(Species!$I13=7,"S","") -> H | J13: =IF(Species!$G13<=Species!$H13,IF(AND(8>=Species!$G13,8<=Species!$H13),"H",""),IF(OR(8>=Species!$G13,8<=Species!$H13),"H",""))&IF(Species!$I13=8,"S","") -> HS | K13: =IF(Species!$G13<=Species!$H13,IF(AND(9>=Species!$G13,9<=Species!$H13),"H",""),IF(OR(9>=Species!$G13,9<=Species!$H13),"H",""))&IF(Species!$I13=9,"S","") -> H | L13: =IF(Species!$G13<=Species!$H13,IF(AND(10>=Species!$G13,10<=Species!$H13),"H",""),IF(OR(10>=Species!$G13,10<=Species!$H13),"H",""))&IF(Species!$I13=10,"S","") | M13: =IF(Species!$G13<=Species!$H13,IF(AND(11>=Species!$G13,11<=Species!$H13),"H",""),IF(OR(11>=Species!$G13,11<=Species!$H13),"H",""))&IF(Species!$I13=11,"S","") | N13: =IF(Species!$G13<=Species!$H13,IF(AND(12>=Species!$G13,12<=Species!$H13),"H",""),IF(OR(12>=Species!$G13,12<=Species!$H13),"H",""))&IF(Species!$I13=12,"S","")
... A186: =Species!B186 -> Bush Honeysuckle Berry | B186: =Species!F186 -> Fruit | C186: =IF(Species!$G186<=Species!$H186,IF(AND(1>=Species!$G186,1<=Species!$H186),"H",""),IF(OR(1>=Species!$G186,1<=Species!$H186),"H",""))&IF(Species!$I186=1,"S","") | D186: =IF(Species!$G186<=Species!$H186,IF(AND(2>=Species!$G186,2<=Species!$H186),"H",""),IF(OR(2>=Species!$G186,2<=Species!$H186),"H",""))&IF(Species!$I186=2,"S","") | E186: =IF(Species!$G186<=Species!$H186,IF(AND(3>=Species!$G186,3<=Species!$H186),"H",""),IF(OR(3>=Species!$G186,3<=Species!$H186),"H",""))&IF(Species!$I186=3,"S","") | F186: =IF(Species!$G186<=Species!$H186,IF(AND(4>=Species!$G186,4<=Species!$H186),"H",""),IF(OR(4>=Species!$G186,4<=Species!$H186),"H",""))&IF(Species!$I186=4,"S","") | G186: =IF(Species!$G186<=Species!$H186,IF(AND(5>=Species!$G186,5<=Species!$H186),"H",""),IF(OR(5>=Species!$G186,5<=Species!$H186),"H",""))&IF(Species!$I186=5,"S","") | H186: =IF(Species!$G186<=Species!$H186,IF(AND(6>=Species!$G186,6<=Species!$H186),"H",""),IF(OR(6>=Species!$G186,6<=Species!$H186),"H",""))&IF(Species!$I186=6,"S","") | I186: =IF(Species!$G186<=Species!$H186,IF(AND(7>=Species!$G186,7<=Species!$H186),"H",""),IF(OR(7>=Species!$G186,7<=Species!$H186),"H",""))&IF(Species!$I186=7,"S","") | J186: =IF(Species!$G186<=Species!$H186,IF(AND(8>=Species!$G186,8<=Species!$H186),"H",""),IF(OR(8>=Species!$G186,8<=Species!$H186),"H",""))&IF(Species!$I186=8,"S","") | K186: =IF(Species!$G186<=Species!$H186,IF(AND(9>=Species!$G186,9<=Species!$H186),"H",""),IF(OR(9>=Species!$G186,9<=Species!$H186),"H",""))&IF(Species!$I186=9,"S","") -> H | L186: =IF(Species!$G186<=Species!$H186,IF(AND(10>=Species!$G186,10<=Species!$H186),"H",""),IF(OR(10>=Species!$G186,10<=Species!$H186),"H",""))&IF(Species!$I186=10,"S","") -> H | M186: =IF(Species!$G186<=Species!$H186,IF(AND(11>=Species!$G186,11<=Species!$H186),"H",""),IF(OR(11>=Species!$G186,11<=Species!$H186),"H",""))&IF(Species!$I186=11,"S","") -> H | N186: =IF(Species!$G186<=Species!$H186,IF(AND(12>=Species!$G186,12<=Species!$H186),"H",""),IF(OR(12>=Species!$G186,12<=Species!$H186),"H",""))&IF(Species!$I186=12,"S","") -> H
A188: Species harvestable | C188: =COUNTIF(C2:C186,"H*") -> 19 | D188: =COUNTIF(D2:D186,"H*") -> 21 | E188: =COUNTIF(E2:E186,"H*") -> 38 | F188: =COUNTIF(F2:F186,"H*") -> 49 | G188: =COUNTIF(G2:G186,"H*") -> 59 | H188: =COUNTIF(H2:H186,"H*") -> 73 | I188: =COUNTIF(I2:I186,"H*") -> 79 | J188: =COUNTIF(J2:J186,"H*") -> 95 | ... N188: =COUNTIF(N2:N186,"H*") -> 24
A189: Legend: H = harvest window, S = seed collection month, HS = both

Sheet Biomes
A1: Biome | B1: Description | C1: Flora Signature | D1: Creature Clues | E1: Dynamics | F1: # Species | G1: # Rare Actives | H1: Avg Toxicity
A2: Disturbed Ground | B2: Field edges, ruins, roads | C2: Common weeds — the tutorial biome; everything you need for basics | D2: Rabbits, sparrows | E2: Abundant; fast regrowth | F2: =COUNTIF(Species!$E$2:$E$186,A2) -> 34 | G2: =COUNTIFS(Species!$E$2:$E$186,A2,Species!$D$2:$D$186,"Rare Active") -> 0 | H2: =IFERROR(AVERAGEIF(Species!$E$2:$E$186,A2,Species!$P$2:$P$186),0) -> 1.4705882
A3: Prairie | B3: Tallgrass remnant; burns every few years | C3: Deep-rooted perennials; fire-dependent species (Ashen Clover) | D3: Bison herd, meadowlarks, prairie chickens | E3: Fire cycle resets patches | F3: =COUNTIF(Species!$E$2:$E$186,A3) -> 30 | G3: =COUNTIFS(Species!$E$2:$E$186,A3,Species!$D$2:$D$186,"Rare Active") -> 2 | H3: =IFERROR(AVERAGEIF(Species!$E$2:$E$186,A3,Species!$P$2:$P$186),0) -> 0.36666667
A4: Oak Savanna | B4: Scattered oaks over grass | C4: Bark, nuts, fruit; dye plants | D4: Deer, wild turkey | E4: Mast years vary | F4: =COUNTIF(Species!$E$2:$E$186,A4) -> 11 | G4: =COUNTIFS(Species!$E$2:$E$186,A4,Species!$D$2:$D$186,"Rare Active") -> 0 | H4: =IFERROR(AVERAGEIF(Species!$E$2:$E$186,A4,Species!$P$2:$P$186),0) -> 1
A5: Upland Forest | B5: Shawnee-style hills, deep shade | C5: Spring ephemerals; the rare root trade (ginseng, goldenseal) | D5: Box turtles, ruffed grouse, black bear (rare) | E5: Overharvest crashes patches for years | F5: =COUNTIF(Species!$E$2:$E$186,A5) -> 39 | G5: =COUNTIFS(Species!$E$2:$E$186,A5,Species!$D$2:$D$186,"Rare Active") -> 5 | H5: =IFERROR(AVERAGEIF(Species!$E$2:$E$186,A5,Species!$P$2:$P$186),0) -> 1.8205128
A6: Bottomland Forest | B6: Floodplain, rich soil | C6: Fruits, nettles, morels after floods | D6: Raccoons, wood ducks, beaver | E6: Floods relocate patches | F6: =COUNTIF(Species!$E$2:$E$186,A6) -> 14 | G6: =COUNTIFS(Species!$E$2:$E$186,A6,Species!$D$2:$D$186,"Rare Active") -> 1 | H6: =IFERROR(AVERAGEIF(Species!$E$2:$E$186,A6,Species!$P$2:$P$186),0) -> 1.5
A7: Riverbank | B7: Gravel bars, river edges | C7: Willow, elder, horsetail | D7: Otters, herons, kingfishers | E7: Season-dependent access | F7: =COUNTIF(Species!$E$2:$E$186,A7) -> 14 | G7: =COUNTIFS(Species!$E$2:$E$186,A7,Species!$D$2:$D$186,"Rare Active") -> 0 | H7: =IFERROR(AVERAGEIF(Species!$E$2:$E$186,A7,Species!$P$2:$P$186),0) -> 2.3571429
A8: Wetland | B8: Marsh, swamp, fen | C8: Starches, bitters, nerve herbs | D8: Muskrats, cottonmouth (venom source), frogs | E8: Water level gates access | F8: =COUNTIF(Species!$E$2:$E$186,A8) -> 15 | G8: =COUNTIFS(Species!$E$2:$E$186,A8,Species!$D$2:$D$186,"Rare Active") -> 0 | H8: =IFERROR(AVERAGEIF(Species!$E$2:$E$186,A8,Species!$P$2:$P$186),0) -> 1.6666667
A9: Limestone Bluff | B9: Cliffs, glades, overhangs | C9: Lichens, cactus, cedar; climbing required | D9: Ravens, timber rattlesnake, bats | E9: Dangerous traverse | F9: =COUNTIF(Species!$E$2:$E$186,A9) -> 9 | G9: =COUNTIFS(Species!$E$2:$E$186,A9,Species!$D$2:$D$186,"Rare Active") -> 1 | H9: =IFERROR(AVERAGEIF(Species!$E$2:$E$186,A9,Species!$P$2:$P$186),0) -> 1.1111111
A10: Old Homestead | B10: Abandoned farms & gardens | C10: Escaped European herbs; old orchards | D10: Feral cats, barn owls, honeybees | E10: Houses ruins/lore | F10: =COUNTIF(Species!$E$2:$E$186,A10) -> 14 | G10: =COUNTIFS(Species!$E$2:$E$186,A10,Species!$D$2:$D$186,"Rare Active") -> 0 | H10: =IFERROR(AVERAGEIF(Species!$E$2:$E$186,A10,Species!$P$2:$P$186),0) -> 1.5
A11: Mycelial Hollow | B11: Sinkholes where the Network surfaces (fictional) | C11: All fictional rare actives | D11: Network-touched creatures | E11: Only reachable after reading the Network | F11: =COUNTIF(Species!$E$2:$E$186,A11) -> 5 | G11: =COUNTIFS(Species!$E$2:$E$186,A11,Species!$D$2:$D$186,"Rare Active") -> 5 | H11: =IFERROR(AVERAGEIF(Species!$E$2:$E$186,A11,Species!$P$2:$P$186),0) -> 1.6

Sheet Animal Products
A1: Product | B1: Source Creature | C1: Harvest Method | D1: Compound Profile | E1: Traditional / Game Use | F1: Ethics & Reputation
A2: Honey | B2: Honeybee (tamed hive) | C2: Harvest frames | D2: SUG8 | E2: Syrups, preservation, wound dressing | F2: Ethical — hive thrives if you leave 1/3
A3: Beeswax | B3: Honeybee (tamed hive) | C3: Render comb | D3: RES (carrier) | E3: Salves, candles, seals | F3: Ethical
A4: Propolis | B4: Honeybee (tamed hive) | C4: Scrape hive | D4: RES6 FLA4 | E4: Antimicrobial tincture | F4: Ethical
A5: Goat Milk | B5: Tamed goat | C5: Milk daily | D5: SUG3 + fat | E5: Soap, cream base | F5: Ethical; bonded goat yields more
A6: Eggs | B6: Tamed hens / turkey | C6: Collect | D6: Protein | E6: Clarifying agent (egg white), binder | F6: Ethical
A7: Wool | B7: Tamed sheep | C7: Shear in spring | D7: — | E7: Strainer cloth, dye trade | F7: Ethical
A8: Shed Antler | B8: Deer | C8: Find in late winter | D8: Mineral | E8: Antler-horn ash, tool handles | F8: Found, not taken
A9: Molted Feathers | B9: Turkey, hawk, owl | C9: Find / gift from bonded birds | D9: — | E9: Ritual smudge fans, quills for labels | F9: Found
A10: Rendered Lard / Tallow | B10: Hunted or farm animal | C10: Render fat | D10: Fat (carrier) | E10: Salve base (cheaper than oil) | F10: Hunting option — local wildlife grows wary
A11: Bear Grease | B11: Black bear | C11: Hunt (rare, reputation hit) | D11: Fat (premium carrier) | E11: Premium salve base; folk hair tonic | F11: Heavy reputation cost; protected status in some regions
A12: Snake Venom | B12: Timber rattlesnake / cottonmouth | C12: Milk a captured snake (skill check) | D12: Venom | E12: Antivenom crafting (with Rattlesnake Master) | F12: Release unharmed for bonus
... A17: Fish Glue | B17: River fish | C17: Boil skins | D17: Protein | E17: Binder for pigments, label adhesive | F17: Byproduct of fishing

Sheet Recipes
A1: Recipe | B1: Ingredient 1 | C1: Ingredient 2 | D1: Ingredient 3 | E1: Method | F1: Protocol Notes (discovered) | G1: Effect / Order Use | H1: Discovery Tier | I1: Ingredient Cost (c) | J1: Suggested Price (c) | L1: Discovery Tier | M1: Markup ×
A2: Bitter Spring Tonic | B2: Dandelion | C2: Burdock | D2: Chicory | E2: Decoction | F2: Simmer 30 min, add honey syrup | G2: Digestion buff; NPC 'sluggish' orders | H2: Starter | I2: =IFERROR(INDEX(Species!$U$2:$U$186,MATCH(B2,Species!$B$2:$B$186,0)),0)+IFERROR(INDEX(Species!$U$2:$U$186,MATCH(C2,Species!$B$2:$B$186,0)),0)+IFERROR(INDEX(Species!$U$2:$U$186,MATCH(D2,Species!$B$2:$B$186,0)),0) -> 35 | J2: =ROUND(I2*INDEX($M$3:$M$7,MATCH(H2,$L$3:$L$7,0)),0) -> 53
A3: Sleepwell Tea | B3: German Chamomile | C3: Basswood Flower | D3: Lemon Balm | E3: Hot Infusion (tea) | F3: Steep ≤7 min (TAN harshness after) | G3: Sleep regen bonus | H3: Starter | I3: =IFERROR(INDEX(Species!$U$2:$U$186,MATCH(B3,Species!$B$2:$B$186,0)),0)+IFERROR(INDEX(Species!$U$2:$U$186,MATCH(C3,Species!$B$2:$B$186,0)),0)+IFERROR(INDEX(Species!$U$2:$U$186,MATCH(D3,Species!$B$2:$B$186,0)),0) -> 68 | J3: =ROUND(I3*INDEX($M$3:$M$7,MATCH(H3,$L$3:$L$7,0)),0) -> 102 | L3: Starter | M3: 1.5
A4: Fever Break | B4: Boneset | C4: Elderflower | D4: Spicebush Twig | E4: Hot Infusion (tea) | F4: Drink hot; bitterness lowers sale price unless masked | G4: Cures fever status | H4: Common | I4: =IFERROR(INDEX(Species!$U$2:$U$186,MATCH(B4,Species!$B$2:$B$186,0)),0)+IFERROR(INDEX(Species!$U$2:$U$186,MATCH(C4,Species!$B$2:$B$186,0)),0)+IFERROR(INDEX(Species!$U$2:$U$186,MATCH(D4,Species!$B$2:$B$186,0)),0) -> 80 | J4: =ROUND(I4*INDEX($M$3:$M$7,MATCH(H4,$L$3:$L$7,0)),0) -> 160 | L4: Common | M4: 2
A5: Elderberry Syrup | B5: Elderberry | C5: Riverbank Grape | D5: Pasture Rose Hip | E5: Syrup | F5: MUST cook elderberry first or batch causes nausea | G5: Illness resistance 3 days | H5: Common | I5: =IFERROR(INDEX(Species!$U$2:$U$186,MATCH(B5,Species!$B$2:$B$186,0)),0)+IFERROR(INDEX(Species!$U$2:$U$186,MATCH(C5,Species!$B$2:$B$186,0)),0)+IFERROR(INDEX(Species!$U$2:$U$186,MATCH(D5,Species!$B$2:$B$186,0)),0) -> 55 | J5: =ROUND(I5*INDEX($M$3:$M$7,MATCH(H5,$L$3:$L$7,0)),0) -> 110 | L5: Uncommon | M5: 3
A6: Wound Salve | B6: Common Yarrow | C6: Self-heal | D6: Calendula (escaped) | E6: Salve | F6: Infuse dry herb in oil 4 hrs warm; 4:1 oil:beeswax | G6: Heals bleeding faster | H6: Common | I6: =IFERROR(INDEX(Species!$U$2:$U$186,MATCH(B6,Species!$B$2:$B$186,0)),0)+IFERROR(INDEX(Species!$U$2:$U$186,MATCH(C6,Species!$B$2:$B$186,0)),0)+IFERROR(INDEX(Species!$U$2:$U$186,MATCH(D6,Species!$B$2:$B$186,0)),0) -> 25 | J6: =ROUND(I6*INDEX($M$3:$M$7,MATCH(H6,$L$3:$L$7,0)),0) -> 50 | L6: Rare | M6: 4
A7: Throat Coat | B7: Slippery Elm | C7: Common Mullein | D7: Wild Cherry Bark | E7: Cold Infusion | F7: Elm cold-steeped; cherry bark decocted separately, then combined | G7: Cough cure; premium order | H7: Uncommon | I7: =IFERROR(INDEX(Species!$U$2:$U$186,MATCH(B7,Species!$B$2:$B$186,0)),0)+IFERROR(INDEX(Species!$U$2:$U$186,MATCH(C7,Species!$B$2:$B$186,0)),0)+IFERROR(INDEX(Species!$U$2:$U$186,MATCH(D7,Species!$B$2:$B$186,0)),0) -> 117 | J7: =ROUND(I7*INDEX($M$3:$M$7,MATCH(H7,$L$3:$L$7,0)),0) -> 351 | L7: Legendary | M7: 8
A8: Calm Drops | B8: Mad-dog Skullcap | C8: Motherwort | D8: Anise Hyssop | E8: Tincture | F8: Hyssop needed to mask motherwort bitter | G8: Anxiety status removed | H8: Uncommon | I8: =IFERROR(INDEX(Species!$U$2:$U$186,MATCH(B8,Species!$B$2:$B$186,0)),0)+IFERROR(INDEX(Species!$U$2:$U$186,MATCH(C8,Species!$B$2:$B$186,0)),0)+IFERROR(INDEX(Species!$U$2:$U$186,MATCH(D8,Species!$B$2:$B$186,0)),0) -> 54 | J8: =ROUND(I8*INDEX($M$3:$M$7,MATCH(H8,$L$3:$L$7,0)),0) -> 162
A9: Ward Tincture | B9: Purple Coneflower | C9: Goldenseal | D9: Elderflower | E9: Tincture | F9: Test root quality by tongue-tingle first | G9: Strong infection cure | H9: Rare | I9: =IFERROR(INDEX(Species!$U$2:$U$186,MATCH(B9,Species!$B$2:$B$186,0)),0)+IFERROR(INDEX(Species!$U$2:$U$186,MATCH(C9,Species!$B$2:$B$186,0)),0)+IFERROR(INDEX(Species!$U$2:$U$186,MATCH(D9,Species!$B$2:$B$186,0)),0) -> 370 | J9: =ROUND(I9*INDEX($M$3:$M$7,MATCH(H9,$L$3:$L$7,0)),0) -> 1480 | L9: Honey isn't a plant, so it prices at 0 here — add it to Species or an Animal price column to include it.
A10: Ironwood Liniment | B10: Wintergreen | C10: Black Willow Bark | D10: Wild Bergamot | E10: Infused Oil | F10: Topical only; ingestion = poisoning event | G10: Muscle soreness removed | H10: Uncommon | I10: =IFERROR(INDEX(Species!$U$2:$U$186,MATCH(B10,Species!$B$2:$B$186,0)),0)+IFERROR(INDEX(Species!$U$2:$U$186,MATCH(C10,Species!$B$2:$B$186,0)),0)+IFERROR(INDEX(Species!$U$2:$U$186,MATCH(D10,Species!$B$2:$B$186,0)),0) -> 98 | J10: =ROUND(I10*INDEX($M$3:$M$7,MATCH(H10,$L$3:$L$7,0)),0) -> 294
A11: Network Censer | B11: Lanternmoss | C11: Eastern Red Cedar | D11: Common Yarrow | E11: Smoke / Burn | F11: Cedar stabilizes smoke; yarrow prevents disorientation | G11: See mycelial map 1 hr | H11: Legendary | I11: =IFERROR(INDEX(Species!$U$2:$U$186,MATCH(B11,Species!$B$2:$B$186,0)),0)+IFERROR(INDEX(Species!$U$2:$U$186,MATCH(C11,Species!$B$2:$B$186,0)),0)+IFERROR(INDEX(Species!$U$2:$U$186,MATCH(D11,Species!$B$2:$B$186,0)),0) -> 335 | J11: =ROUND(I11*INDEX($M$3:$M$7,MATCH(H11,$L$3:$L$7,0)),0) -> 2680
A12: Hollowsong | B12: Hollowbell | C12: Sweetflag | D12: Honey | E12: Tincture | F12: Sweetflag clarifies voice; hum in VR mic to locate roots | G12: Echolocate relics | H12: Legendary | I12: =IFERROR(INDEX(Species!$U$2:$U$186,MATCH(B12,Species!$B$2:$B$186,0)),0)+IFERROR(INDEX(Species!$U$2:$U$186,MATCH(C12,Species!$B$2:$B$186,0)),0)+IFERROR(INDEX(Species!$U$2:$U$186,MATCH(D12,Species!$B$2:$B$186,0)),0) -> 346 | J12: =ROUND(I12*INDEX($M$3:$M$7,MATCH(H12,$L$3:$L$7,0)),0) -> 2768
A13: Tree-Tongue | B13: Weeping Rhizine | C13: Basswood Flower | D13: Graftwort | E13: Fresh only (no drying) | F13: Rhizine dies on drying; brew within 2 in-game days | G13: Converse with one tree/creature | H13: Legendary | I13: =IFERROR(INDEX(Species!$U$2:$U$186,MATCH(B13,Species!$B$2:$B$186,0)),0)+IFERROR(INDEX(Species!$U$2:$U$186,MATCH(C13,Species!$B$2:$B$186,0)),0)+IFERROR(INDEX(Species!$U$2:$U$186,MATCH(D13,Species!$B$2:$B$186,0)),0) -> 649 | J13: =ROUND(I13*INDEX($M$3:$M$7,MATCH(H13,$L$3:$L$7,0)),0) -> 5192
A14: Persimmon Cordial | B14: Persimmon | C14: Spicebush Berry | D14: Honey | E14: Ferment | F14: Unripe persimmon = chalky failure; wait for first frost | G14: High-value trade good | H14: Common | I14: =IFERROR(INDEX(Species!$U$2:$U$186,MATCH(B14,Species!$B$2:$B$186,0)),0)+IFERROR(INDEX(Species!$U$2:$U$186,MATCH(C14,Species!$B$2:$B$186,0)),0)+IFERROR(INDEX(Species!$U$2:$U$186,MATCH(D14,Species!$B$2:$B$186,0)),0) -> 34 | J14: =ROUND(I14*INDEX($M$3:$M$7,MATCH(H14,$L$3:$L$7,0)),0) -> 68
A15: Acorn Flour | B15: White Oak Acorn | C15: — | D15: — | E15: Leach | F15: Change water until bitterness gone (taste test) | G15: Food / binder ingredient | H15: Starter | I15: =IFERROR(INDEX(Species!$U$2:$U$186,MATCH(B15,Species!$B$2:$B$186,0)),0)+IFERROR(INDEX(Species!$U$2:$U$186,MATCH(C15,Species!$B$2:$B$186,0)),0)+IFERROR(INDEX(Species!$U$2:$U$186,MATCH(D15,Species!$B$2:$B$186,0)),0) -> 13 | J15: =ROUND(I15*INDEX($M$3:$M$7,MATCH(H15,$L$3:$L$7,0)),0) -> 20
A16: Walnut Ink | B16: Black Walnut Hull | C16: Smooth Sumac Leaf | D16: Fish Glue | E16: Mordant Dye | F16: Iron mordant → black ink | G16: Label ink; scribe orders | H16: Common | I16: =IFERROR(INDEX(Species!$U$2:$U$186,MATCH(B16,Species!$B$2:$B$186,0)),0)+IFERROR(INDEX(Species!$U$2:$U$186,MATCH(C16,Species!$B$2:$B$186,0)),0)+IFERROR(INDEX(Species!$U$2:$U$186,MATCH(D16,Species!$B$2:$B$186,0)),0) -> 55 | J16: =ROUND(I16*INDEX($M$3:$M$7,MATCH(H16,$L$3:$L$7,0)),0) -> 110

Sheet Stats
A1: Roster Balance (live)
A3: Tier | B3: Count | C3: % of Roster | D3: Target % | E3: Avg Toxicity | F3: Avg Base Price (c)
A4: Base | B4: =COUNTIF(Species!$D$2:$D$186,A4) -> 100 | C4: =B4/$B$7 -> 0.54054054 | D4: 0.6 | E4: =AVERAGEIF(Species!$D$2:$D$186,A4,Species!$P$2:$P$186) -> 1.02 | F4: =AVERAGEIF(Species!$D$2:$D$186,A4,Species!$U$2:$U$186) -> 11.07
A5: Workhorse | B5: =COUNTIF(Species!$D$2:$D$186,A5) -> 71 | C5: =B5/$B$7 -> 0.38378378 | D5: 0.3 | E5: =AVERAGEIF(Species!$D$2:$D$186,A5,Species!$P$2:$P$186) -> 1.8873239 | F5: =AVERAGEIF(Species!$D$2:$D$186,A5,Species!$U$2:$U$186) -> 36.971831
A6: Rare Active | B6: =COUNTIF(Species!$D$2:$D$186,A6) -> 14 | C6: =B6/$B$7 -> 0.075675676 | D6: 0.1 | E6: =AVERAGEIF(Species!$D$2:$D$186,A6,Species!$P$2:$P$186) -> 1.7857143 | F6: =AVERAGEIF(Species!$D$2:$D$186,A6,Species!$U$2:$U$186) -> 282.14286
A7: Total | B7: =SUM(B4:B6) -> 185
A9: Toxic species (≥5) | B9: =COUNTIF(Species!$P$2:$P$186,">=5") -> 25
A10: Lethal species (≥9) | B10: =COUNTIF(Species!$P$2:$P$186,">=9") -> 5
A11: Fictional species | B11: =COUNTIF(Species!$C$2:$C$186,"*fictional*") -> 9
A12: Peak harvest month (count) | B12: =MAX('Seasonal Calendar'!C188:N188) -> 127
A13: Leanest month (count) | B13: =MIN('Seasonal Calendar'!C188:N188) -> 19
